Workbook

Sheet Janeiro
B2: Janeiro | Z2: Categoria | AA2: Valor gasto
R3: Saldo: | S3: =S10-S18 -> 0 | U3: Gastos do mês por categoria: | Z3: =U5 -> Mercado | AA3: =W5 -> 0
B4: Total de gastos: | F4: =F7+F20+N4 -> 0 | J4: Total de Gastos do Mês: | N4: =SUM(P8:P35) -> 0 | U4: Categoria | V4: Valor esperado | W4: Valor gasto | X4: Porcentagem | Z4: =U6 -> Despesas eventuais | AA4: =W6 -> 0
U5: Mercado | W5: =SUMIF($G$11:$G$18,U5,$H$11:$H$18)+SUMIF($G$24:$G$35,U5,$H$24:$H$35)+SUMIF($N$8:$N$35,U5,$P$8:$P$35) -> 0 | X5: =IF($F$4=0,0,W5/$F$4) -> 0 | Z5: =U7 -> Necessidades | AA5: =W7 -> 0
J6: Gastos do Mês | U6: Despesas eventuais | W6: =SUMIF($G$11:$G$18,U6,$H$11:$H$18)+SUMIF($G$24:$G$35,U6,$H$24:$H$35)+SUMIF($N$8:$N$35,U6,$P$8:$P$35) -> 0 | X6: =IF($F$4=0,0,W6/$F$4) -> 0 | Z6: =U8 -> Roupa | AA6: =W8 -> 0
B7: Total de Fixos: | F7: =SUM(H11:H18) -> 0 | J7: Nome | L7: Data | M7: Tipo | N7: Categoria | P7: Valor | R7: Entradas | U7: Necessidades | W7: =SUMIF($G$11:$G$18,U7,$H$11:$H$18)+SUMIF($G$24:$G$35,U7,$H$24:$H$35)+SUMIF($N$8:$N$35,U7,$P$8:$P$35) -> 0 | X7: =IF($F$4=0,0,W7/$F$4) -> 0 | Z7: =U9 -> Saúde | AA7: =W9 -> 0
R8: Salário | U8: Roupa | W8: =SUMIF($G$11:$G$18,U8,$H$11:$H$18)+SUMIF($G$24:$G$35,U8,$H$24:$H$35)+SUMIF($N$8:$N$35,U8,$P$8:$P$35) -> 0 | X8: =IF($F$4=0,0,W8/$F$4) -> 0 | Z8: =U10 -> Presentes | AA8: =W10 -> 0
B9: Fixos | R9: Bônus | U9: Saúde | W9: =SUMIF($G$11:$G$18,U9,$H$11:$H$18)+SUMIF($G$24:$G$35,U9,$H$24:$H$35)+SUMIF($N$8:$N$35,U9,$P$8:$P$35) -> 0 | X9: =IF($F$4=0,0,W9/$F$4) -> 0 | Z9: =U11 -> Beleza | AA9: =W11 -> 0
B10: Nome | D10: Pago? | E10: Data | F10: Tipo | G10: Categoria | H10: Valor | R10: Total | S10: =SUM(S8:S9) -> 0 | U10: Presentes | W10: =SUMIF($G$11:$G$18,U10,$H$11:$H$18)+SUMIF($G$24:$G$35,U10,$H$24:$H$35)+SUMIF($N$8:$N$35,U10,$P$8:$P$35) -> 0 | X10: =IF($F$4=0,0,W10/$F$4) -> 0 | Z10: =U12 -> Desenvolvimento | AA10: =W12 -> 0
U11: Beleza | W11: =SUMIF($G$11:$G$18,U11,$H$11:$H$18)+SUMIF($G$24:$G$35,U11,$H$24:$H$35)+SUMIF($N$8:$N$35,U11,$P$8:$P$35) -> 0 | X11: =IF($F$4=0,0,W11/$F$4) -> 0 | Z11: =U13 -> Lazer | AA11: =W13 -> 0
R12: Saídas | U12: Desenvolvimento | W12: =SUMIF($G$11:$G$18,U12,$H$11:$H$18)+SUMIF($G$24:$G$35,U12,$H$24:$H$35)+SUMIF($N$8:$N$35,U12,$P$8:$P$35) -> 0 | X12: =IF($F$4=0,0,W12/$F$4) -> 0 | Z12: =U14 -> Eletrônicos | AA12: =W14 -> 0
R13: Débito | S13: =SUMIF($F$11:$F$18,R13,$H$11:$H$18)+SUMIF($F$24:$F$35,R13,$H$24:$H$35)+SUMIF($M$8:$M$35,R13,$P$8:$P$35) -> 0 | U13: Lazer | W13: =SUMIF($G$11:$G$18,U13,$H$11:$H$18)+SUMIF($G$24:$G$35,U13,$H$24:$H$35)+SUMIF($N$8:$N$35,U13,$P$8:$P$35) -> 0 | X13: =IF($F$4=0,0,W13/$F$4) -> 0 | Z13: =U15 -> Assinaturas | AA13: =W15 -> 0
R14: Nubank | S14: =SUMIF($F$11:$F$18,R14,$H$11:$H$18)+SUMIF($F$24:$F$35,R14,$H$24:$H$35)+SUMIF($M$8:$M$35,R14,$P$8:$P$35) -> 0 | U14: Eletrônicos | W14: =SUMIF($G$11:$G$18,U14,$H$11:$H$18)+SUMIF($G$24:$G$35,U14,$H$24:$H$35)+SUMIF($N$8:$N$35,U14,$P$8:$P$35) -> 0 | X14: =IF($F$4=0,0,W14/$F$4) -> 0 | Z14: =U16 -> Uber transporte | AA14: =W16 -> 0
R15: Inter | S15: =SUMIF($F$11:$F$18,R15,$H$11:$H$18)+SUMIF($F$24:$F$35,R15,$H$24:$H$35)+SUMIF($M$8:$M$35,R15,$P$8:$P$35) -> 0 | U15: Assinaturas | W15: =SUMIF($G$11:$G$18,U15,$H$11:$H$18)+SUMIF($G$24:$G$35,U15,$H$24:$H$35)+SUMIF($N$8:$N$35,U15,$P$8:$P$35) -> 0 | X15: =IF($F$4=0,0,W15/$F$4) -> 0 | Z15: =U17 -> iFood/restaurante | AA15: =W17 -> 0
R16: Itaú | S16: =SUMIF($F$11:$F$18,R16,$H$11:$H$18)+SUMIF($F$24:$F$35,R16,$H$24:$H$35)+SUMIF($M$8:$M$35,R16,$P$8:$P$35) -> 0 | U16: Uber transporte | W16: =SUMIF($G$11:$G$18,U16,$H$11:$H$18)+SUMIF($G$24:$G$35,U16,$H$24:$H$35)+SUMIF($N$8:$N$35,U16,$P$8:$P$35) -> 0 | X16: =IF($F$4=0,0,W16/$F$4) -> 0 | Z16: =U18 -> Comida faculdade | AA16: =W18 -> 0
R17: Investimentos | S17: =S23 -> 0 | U17: iFood/restaurante | W17: =SUMIF($G$11:$G$18,U17,$H$11:$H$18)+SUMIF($G$24:$G$35,U17,$H$24:$H$35)+SUMIF($N$8:$N$35,U17,$P$8:$P$35) -> 0 | X17: =IF($F$4=0,0,W17/$F$4) -> 0 | Z17: =U19 -> Contas | AA17: =W19 -> 0
R18: Total | S18: =SUM(S13:S17) -> 0 | U18: Comida faculdade | W18: =SUMIF($G$11:$G$18,U18,$H$11:$H$18)+SUMIF($G$24:$G$35,U18,$H$24:$H$35)+SUMIF($N$8:$N$35,U18,$P$8:$P$35) -> 0 | X18: =IF($F$4=0,0,W18/$F$4) -> 0 | Z18: =U20 -> Outros | AA18: =W20 -> 0
U19: Contas | W19: =SUMIF($G$11:$G$18,U19,$H$11:$H$18)+SUMIF($G$24:$G$35,U19,$H$24:$H$35)+SUMIF($N$8:$N$35,U19,$P$8:$P$35) -> 0 | X19: =IF($F$4=0,0,W19/$F$4) -> 0
B20: Total de Parcelamentos | F20: =SUM(H24:H35) -> 0 | R20: Investimentos | U20: Outros | W20: =SUMIF($G$11:$G$18,U20,$H$11:$H$18)+SUMIF($G$24:$G$35,U20,$H$24:$H$35)+SUMIF($N$8:$N$35,U20,$P$8:$P$35) -> 0 | X20: =IF($F$4=0,0,W20/$F$4) -> 0
R21: Reserva
B22: Parcelamentos | R22: Renda fixa | U22: Gastos por tipo de pagamento
B23: Nome | D23: Parcelas | E23: Data | F23: Tipo | G23: Categoria | H23: Valor | R23: Total | S23: =SUM(S21:S22) -> 0 | U23: Tipo | V23: Valor | W23: Data | X23: Pago?
U24: Débito | V24: =S13 -> 0 | X24: ☐
U25: Nubank | V25: =S14 -> 0 | X25: ☐
U26: Inter | V26: =S15 -> 0 | X26: ☐
U27: Itaú | V27: =S16 -> 0 | X27: ☐
R30: Porcentagem de gastos por categoria

Sheet Fevereiro
B2: Fevereiro | Z2: Categoria | AA2: Valor gasto
R3: Saldo: | S3: =S10-S18 -> 0 | U3: Gastos do mês por categoria: | Z3: =U5 -> Mercado | AA3: =W5 -> 0
B4: Total de gastos: | F4: =F7+F20+N4 -> 0 | J4: Total de Gastos do Mês: | N4: =SUM(P8:P35) -> 0 | U4: Categoria | V4: Valor esperado | W4: Valor gasto | X4: Porcentagem | Z4: =U6 -> Despesas eventuais | AA4: =W6 -> 0
U5: Mercado | W5: =SUMIF($G$11:$G$18,U5,$H$11:$H$18)+SUMIF($G$24:$G$35,U5,$H$24:$H$35)+SUMIF($N$8:$N$35,U5,$P$8:$P$35) -> 0 | X5: =IF($F$4=0,0,W5/$F$4) -> 0 | Z5: =U7 -> Necessidades | AA5: =W7 -> 0
J6: Gastos do Mês | U6: Despesas eventuais | W6: =SUMIF($G$11:$G$18,U6,$H$11:$H$18)+SUMIF($G$24:$G$35,U6,$H$24:$H$35)+SUMIF($N$8:$N$35,U6,$P$8:$P$35) -> 0 | X6: =IF($F$4=0,0,W6/$F$4) -> 0 | Z6: =U8 -> Roupa | AA6: =W8 -> 0
B7: Total de Fixos: | F7: =SUM(H11:H18) -> 0 | J7: Nome | L7: Data | M7: Tipo | N7: Categoria | P7: Valor | R7: Entradas | U7: Necessidades | W7: =SUMIF($G$11:$G$18,U7,$H$11:$H$18)+SUMIF($G$24:$G$35,U7,$H$24:$H$35)+SUMIF($N$8:$N$35,U7,$P$8:$P$35) -> 0 | X7: =IF($F$4=0,0,W7/$F$4) -> 0 | Z7: =U9 -> Saúde | AA7: =W9 -> 0
R8: Salário | U8: Roupa | W8: =SUMIF($G$11:$G$18,U8,$H$11:$H$18)+SUMIF($G$24:$G$35,U8,$H$24:$H$35)+SUMIF($N$8:$N$35,U8,$P$8:$P$35) -> 0 | X8: =IF($F$4=0,0,W8/$F$4) -> 0 | Z8: =U10 -> Presentes | AA8: =W10 -> 0
B9: Fixos | R9: Bônus | U9: Saúde | W9: =SUMIF($G$11:$G$18,U9,$H$11:$H$18)+SUMIF($G$24:$G$35,U9,$H$24:$H$35)+SUMIF($N$8:$N$35,U9,$P$8:$P$35) -> 0 | X9: =IF($F$4=0,0,W9/$F$4) -> 0 | Z9: =U11 -> Beleza | AA9: =W11 -> 0
B10: Nome | D10: Pago? | E10: Data | F10: Tipo | G10: Categoria | H10: Valor | R10: Total | S10: =SUM(S8:S9) -> 0 | U10: Presentes | W10: =SUMIF($G$11:$G$18,U10,$H$11:$H$18)+SUMIF($G$24:$G$35,U10,$H$24:$H$35)+SUMIF($N$8:$N$35,U10,$P$8:$P$35) -> 0 | X10: =IF($F$4=0,0,W10/$F$4) -> 0 | Z10: =U12 -> Desenvolvimento | AA10: =W12 -> 0
U11: Beleza | W11: =SUMIF($G$11:$G$18,U11,$H$11:$H$18)+SUMIF($G$24:$G$35,U11,$H$24:$H$35)+SUMIF($N$8:$N$35,U11,$P$8:$P$35) -> 0 | X11: =IF($F$4=0,0,W11/$F$4) -> 0 | Z11: =U13 -> Lazer | AA11: =W13 -> 0
R12: Saídas | U12: Desenvolvimento | W12: =SUMIF($G$11:$G$18,U12,$H$11:$H$18)+SUMIF($G$24:$G$35,U12,$H$24:$H$35)+SUMIF($N$8:$N$35,U12,$P$8:$P$35) -> 0 | X12: =IF($F$4=0,0,W12/$F$4) -> 0 | Z12: =U14 -> Eletrônicos | AA12: =W14 -> 0
R13: Débito | S13: =SUMIF($F$11:$F$18,R13,$H$11:$H$18)+SUMIF($F$24:$F$35,R13,$H$24:$H$35)+SUMIF($M$8:$M$35,R13,$P$8:$P$35) -> 0 | U13: Lazer | W13: =SUMIF($G$11:$G$18,U13,$H$11:$H$18)+SUMIF($G$24:$G$35,U13,$H$24:$H$35)+SUMIF($N$8:$N$35,U13,$P$8:$P$35) -> 0 | X13: =IF($F$4=0,0,W13/$F$4) -> 0 | Z13: =U15 -> Assinaturas | AA13: =W15 -> 0
R14: Nubank | S14: =SUMIF($F$11:$F$18,R14,$H$11:$H$18)+SUMIF($F$24:$F$35,R14,$H$24:$H$35)+SUMIF($M$8:$M$35,R14,$P$8:$P$35) -> 0 | U14: Eletrônicos | W14: =SUMIF($G$11:$G$18,U14,$H$11:$H$18)+SUMIF($G$24:$G$35,U14,$H$24:$H$35)+SUMIF($N$8:$N$35,U14,$P$8:$P$35) -> 0 | X14: =IF($F$4=0,0,W14/$F$4) -> 0 | Z14: =U16 -> Uber transporte | AA14: =W16 -> 0
R15: Inter | S15: =SUMIF($F$11:$F$18,R15,$H$11:$H$18)+SUMIF($F$24:$F$35,R15,$H$24:$H$35)+SUMIF($M$8:$M$35,R15,$P$8:$P$35) -> 0 | U15: Assinaturas | W15: =SUMIF($G$11:$G$18,U15,$H$11:$H$18)+SUMIF($G$24:$G$35,U15,$H$24:$H$35)+SUMIF($N$8:$N$35,U15,$P$8:$P$35) -> 0 | X15: =IF($F$4=0,0,W15/$F$4) -> 0 | Z15: =U17 -> iFood/restaurante | AA15: =W17 -> 0
R16: Itaú | S16: =SUMIF($F$11:$F$18,R16,$H$11:$H$18)+SUMIF($F$24:$F$35,R16,$H$24:$H$35)+SUMIF($M$8:$M$35,R16,$P$8:$P$35) -> 0 | U16: Uber transporte | W16: =SUMIF($G$11:$G$18,U16,$H$11:$H$18)+SUMIF($G$24:$G$35,U16,$H$24:$H$35)+SUMIF($N$8:$N$35,U16,$P$8:$P$35) -> 0 | X16: =IF($F$4=0,0,W16/$F$4) -> 0 | Z16: =U18 -> Comida faculdade | AA16: =W18 -> 0
R17: Investimentos | S17: =S23 -> 0 | U17: iFood/restaurante | W17: =SUMIF($G$11:$G$18,U17,$H$11:$H$18)+SUMIF($G$24:$G$35,U17,$H$24:$H$35)+SUMIF($N$8:$N$35,U17,$P$8:$P$35) -> 0 | X17: =IF($F$4=0,0,W17/$F$4) -> 0 | Z17: =U19 -> Contas | AA17: =W19 -> 0
R18: Total | S18: =SUM(S13:S17) -> 0 | U18: Comida faculdade | W18: =SUMIF($G$11:$G$18,U18,$H$11:$H$18)+SUMIF($G$24:$G$35,U18,$H$24:$H$35)+SUMIF($N$8:$N$35,U18,$P$8:$P$35) -> 0 | X18: =IF($F$4=0,0,W18/$F$4) -> 0 | Z18: =U20 -> Outros | AA18: =W20 -> 0
U19: Contas | W19: =SUMIF($G$11:$G$18,U19,$H$11:$H$18)+SUMIF($G$24:$G$35,U19,$H$24:$H$35)+SUMIF($N$8:$N$35,U19,$P$8:$P$35) -> 0 | X19: =IF($F$4=0,0,W19/$F$4) -> 0
B20: Total de Parcelamentos | F20: =SUM(H24:H35) -> 0 | R20: Investimentos | U20: Outros | W20: =SUMIF($G$11:$G$18,U20,$H$11:$H$18)+SUMIF($G$24:$G$35,U20,$H$24:$H$35)+SUMIF($N$8:$N$35,U20,$P$8:$P$35) -> 0 | X20: =IF($F$4=0,0,W20/$F$4) -> 0
R21: Reserva
B22: Parcelamentos | R22: Renda fixa | U22: Gastos por tipo de pagamento
B23: Nome | D23: Parcelas | E23: Data | F23: Tipo | G23: Categoria | H23: Valor | R23: Total | S23: =SUM(S21:S22) -> 0 | U23: Tipo | V23: Valor | W23: Data | X23: Pago?
U24: Débito | V24: =S13 -> 0 | X24: ☐
U25: Nubank | V25: =S14 -> 0 | X25: ☐
U26: Inter | V26: =S15 -> 0 | X26: ☐
U27: Itaú | V27: =S16 -> 0 | X27: ☐
R30: Porcentagem de gastos por categoria

Sheet Março
B2: Março | Z2: Categoria | AA2: Valor gasto
R3: Saldo: | S3: =S10-S18 -> 0 | U3: Gastos do mês por categoria: | Z3: =U5 -> Mercado | AA3: =W5 -> 0
B4: Total de gastos: | F4: =F7+F20+N4 -> 0 | J4: Total de Gastos do Mês: | N4: =SUM(P8:P35) -> 0 | U4: Categoria | V4: Valor esperado | W4: Valor gasto | X4: Porcentagem | Z4: =U6 -> Despesas eventuais | AA4: =W6 -> 0
U5: Mercado | W5: =SUMIF($G$11:$G$18,U5,$H$11:$H$18)+SUMIF($G$24:$G$35,U5,$H$24:$H$35)+SUMIF($N$8:$N$35,U5,$P$8:$P$35) -> 0 | X5: =IF($F$4=0,0,W5/$F$4) -> 0 | Z5: =U7 -> Necessidades | AA5: =W7 -> 0
J6: Gastos do Mês | U6: Despesas eventuais | W6: =SUMIF($G$11:$G$18,U6,$H$11:$H$18)+SUMIF($G$24:$G$35,U6,$H$24:$H$35)+SUMIF($N$8:$N$35,U6,$P$8:$P$35) -> 0 | X6: =IF($F$4=0,0,W6/$F$4) -> 0 | Z6: =U8 -> Roupa | AA6: =W8 -> 0
B7: Total de Fixos: | F7: =SUM(H11:H18) -> 0 | J7: Nome | L7: Data | M7: Tipo | N7: Categoria | P7: Valor | R7: Entradas | U7: Necessidades | W7: =SUMIF($G$11:$G$18,U7,$H$11:$H$18)+SUMIF($G$24:$G$35,U7,$H$24:$H$35)+SUMIF($N$8:$N$35,U7,$P$8:$P$35) -> 0 | X7: =IF($F$4=0,0,W7/$F$4) -> 0 | Z7: =U9 -> Saúde | AA7: =W9 -> 0
R8: Salário | U8: Roupa | W8: =SUMIF($G$11:$G$18,U8,$H$11:$H$18)+SUMIF($G$24:$G$35,U8,$H$24:$H$35)+SUMIF($N$8:$N$35,U8,$P$8:$P$35) -> 0 | X8: =IF($F$4=0,0,W8/$F$4) -> 0 | Z8: =U10 -> Presentes | AA8: =W10 -> 0
B9: Fixos | R9: Bônus | U9: Saúde | W9: =SUMIF($G$11:$G$18,U9,$H$11:$H$18)+SUMIF($G$24:$G$35,U9,$H$24:$H$35)+SUMIF($N$8:$N$35,U9,$P$8:$P$35) -> 0 | X9: =IF($F$4=0,0,W9/$F$4) -> 0 | Z9: =U11 -> Beleza | AA9: =W11 -> 0
B10: Nome | D10: Pago? | E10: Data | F10: Tipo | G10: Categoria | H10: Valor | R10: Total | S10: =SUM(S8:S9) -> 0 | U10: Presentes | W10: =SUMIF($G$11:$G$18,U10,$H$11:$H$18)+SUMIF($G$24:$G$35,U10,$H$24:$H$35)+SUMIF($N$8:$N$35,U10,$P$8:$P$35) -> 0 | X10: =IF($F$4=0,0,W10/$F$4) -> 0 | Z10: =U12 -> Desenvolvimento | AA10: =W12 -> 0
U11: Beleza | W11: =SUMIF($G$11:$G$18,U11,$H$11:$H$18)+SUMIF($G$24:$G$35,U11,$H$24:$H$35)+SUMIF($N$8:$N$35,U11,$P$8:$P$35) -> 0 | X11: =IF($F$4=0,0,W11/$F$4) -> 0 | Z11: =U13 -> Lazer | AA11: =W13 -> 0
R12: Saídas | U12: Desenvolvimento | W12: =SUMIF($G$11:$G$18,U12,$H$11:$H$18)+SUMIF($G$24:$G$35,U12,$H$24:$H$35)+SUMIF($N$8:$N$35,U12,$P$8:$P$35) -> 0 | X12: =IF($F$4=0,0,W12/$F$4) -> 0 | Z12: =U14 -> Eletrônicos | AA12: =W14 -> 0
R13: Débito | S13: =SUMIF($F$11:$F$18,R13,$H$11:$H$18)+SUMIF($F$24:$F$35,R13,$H$24:$H$35)+SUMIF($M$8:$M$35,R13,$P$8:$P$35) -> 0 | U13: Lazer | W13: =SUMIF($G$11:$G$18,U13,$H$11:$H$18)+SUMIF($G$24:$G$35,U13,$H$24:$H$35)+SUMIF($N$8:$N$35,U13,$P$8:$P$35) -> 0 | X13: =IF($F$4=0,0,W13/$F$4) -> 0 | Z13: =U15 -> Assinaturas | AA13: =W15 -> 0
R14: Nubank | S14: =SUMIF($F$11:$F$18,R14,$H$11:$H$18)+SUMIF($F$24:$F$35,R14,$H$24:$H$35)+SUMIF($M$8:$M$35,R14,$P$8:$P$35) -> 0 | U14: Eletrônicos | W14: =SUMIF($G$11:$G$18,U14,$H$11:$H$18)+SUMIF($G$24:$G$35,U14,$H$24:$H$35)+SUMIF($N$8:$N$35,U14,$P$8:$P$35) -> 0 | X14: =IF($F$4=0,0,W14/$F$4) -> 0 | Z14: =U16 -> Uber transporte | AA14: =W16 -> 0
R15: Inter | S15: =SUMIF($F$11:$F$18,R15,$H$11:$H$18)+SUMIF($F$24:$F$35,R15,$H$24:$H$35)+SUMIF($M$8:$M$35,R15,$P$8:$P$35) -> 0 | U15: Assinaturas | W15: =SUMIF($G$11:$G$18,U15,$H$11:$H$18)+SUMIF($G$24:$G$35,U15,$H$24:$H$35)+SUMIF($N$8:$N$35,U15,$P$8:$P$35) -> 0 | X15: =IF($F$4=0,0,W15/$F$4) -> 0 | Z15: =U17 -> iFood/restaurante | AA15: =W17 -> 0
R16: Itaú | S16: =SUMIF($F$11:$F$18,R16,$H$11:$H$18)+SUMIF($F$24:$F$35,R16,$H$24:$H$35)+SUMIF($M$8:$M$35,R16,$P$8:$P$35) -> 0 | U16: Uber transporte | W16: =SUMIF($G$11:$G$18,U16,$H$11:$H$18)+SUMIF($G$24:$G$35,U16,$H$24:$H$35)+SUMIF($N$8:$N$35,U16,$P$8:$P$35) -> 0 | X16: =IF($F$4=0,0,W16/$F$4) -> 0 | Z16: =U18 -> Comida faculdade | AA16: =W18 -> 0
R17: Investimentos | S17: =S23 -> 0 | U17: iFood/restaurante | W17: =SUMIF($G$11:$G$18,U17,$H$11:$H$18)+SUMIF($G$24:$G$35,U17,$H$24:$H$35)+SUMIF($N$8:$N$35,U17,$P$8:$P$35) -> 0 | X17: =IF($F$4=0,0,W17/$F$4) -> 0 | Z17: =U19 -> Contas | AA17: =W19 -> 0
R18: Total | S18: =SUM(S13:S17) -> 0 | U18: Comida faculdade | W18: =SUMIF($G$11:$G$18,U18,$H$11:$H$18)+SUMIF($G$24:$G$35,U18,$H$24:$H$35)+SUMIF($N$8:$N$35,U18,$P$8:$P$35) -> 0 | X18: =IF($F$4=0,0,W18/$F$4) -> 0 | Z18: =U20 -> Outros | AA18: =W20 -> 0
U19: Contas | W19: =SUMIF($G$11:$G$18,U19,$H$11:$H$18)+SUMIF($G$24:$G$35,U19,$H$24:$H$35)+SUMIF($N$8:$N$35,U19,$P$8:$P$35) -> 0 | X19: =IF($F$4=0,0,W19/$F$4) -> 0
B20: Total de Parcelamentos | F20: =SUM(H24:H35) -> 0 | R20: Investimentos | U20: Outros | W20: =SUMIF($G$11:$G$18,U20,$H$11:$H$18)+SUMIF($G$24:$G$35,U20,$H$24:$H$35)+SUMIF($N$8:$N$35,U20,$P$8:$P$35) -> 0 | X20: =IF($F$4=0,0,W20/$F$4) -> 0
R21: Reserva
B22: Parcelamentos | R22: Renda fixa | U22: Gastos por tipo de pagamento
B23: Nome | D23: Parcelas | E23: Data | F23: Tipo | G23: Categoria | H23: Valor | R23: Total | S23: =SUM(S21:S22) -> 0 | U23: Tipo | V23: Valor | W23: Data | X23: Pago?
U24: Débito | V24: =S13 -> 0 | X24: ☐
U25: Nubank | V25: =S14 -> 0 | X25: ☐
U26: Inter | V26: =S15 -> 0 | X26: ☐
U27: Itaú | V27: =S16 -> 0 | X27: ☐
R30: Porcentagem de gastos por categoria

Sheet Abril
B2: Abril | Z2: Categoria | AA2: Valor gasto
R3: Saldo: | S3: =S10-S18 -> 0 | U3: Gastos do mês por categoria: | Z3: =U5 -> Mercado | AA3: =W5 -> 0
B4: Total de gastos: | F4: =F7+F20+N4 -> 0 | J4: Total de Gastos do Mês: | N4: =SUM(P8:P35) -> 0 | U4: Categoria | V4: Valor esperado | W4: Valor gasto | X4: Porcentagem | Z4: =U6 -> Despesas eventuais | AA4: =W6 -> 0
U5: Mercado | W5: =SUMIF($G$11:$G$18,U5,$H$11:$H$18)+SUMIF($G$24:$G$35,U5,$H$24:$H$35)+SUMIF($N$8:$N$35,U5,$P$8:$P$35) -> 0 | X5: =IF($F$4=0,0,W5/$F$4) -> 0 | Z5: =U7 -> Necessidades | AA5: =W7 -> 0
J6: Gastos do Mês | U6: Despesas eventuais | W6: =SUMIF($G$11:$G$18,U6,$H$11:$H$18)+SUMIF($G$24:$G$35,U6,$H$24:$H$35)+SUMIF($N$8:$N$35,U6,$P$8:$P$35) -> 0 | X6: =IF($F$4=0,0,W6/$F$4) -> 0 | Z6: =U8 -> Roupa | AA6: =W8 -> 0
B7: Total de Fixos: | F7: =SUM(H11:H18) -> 0 | J7: Nome | L7: Data | M7: Tipo | N7: Categoria | P7: Valor | R7: Entradas | U7: Necessidades | W7: =SUMIF($G$11:$G$18,U7,$H$11:$H$18)+SUMIF($G$24:$G$35,U7,$H$24:$H$35)+SUMIF($N$8:$N$35,U7,$P$8:$P$35) -> 0 | X7: =IF($F$4=0,0,W7/$F$4) -> 0 | Z7: =U9 -> Saúde | AA7: =W9 -> 0
R8: Salário | U8: Roupa | W8: =SUMIF($G$11:$G$18,U8,$H$11:$H$18)+SUMIF($G$24:$G$35,U8,$H$24:$H$35)+SUMIF($N$8:$N$35,U8,$P$8:$P$35) -> 0 | X8: =IF($F$4=0,0,W8/$F$4) -> 0 | Z8: =U10 -> Presentes | AA8: =W10 -> 0
B9: Fixos | R9: Bônus | U9: Saúde | W9: =SUMIF($G$11:$G$18,U9,$H$11:$H$18)+SUMIF($G$24:$G$35,U9,$H$24:$H$35)+SUMIF($N$8:$N$35,U9,$P$8:$P$35) -> 0 | X9: =IF($F$4=0,0,W9/$F$4) -> 0 | Z9: =U11 -> Beleza | AA9: =W11 -> 0
B10: Nome | D10: Pago? | E10: Data | F10: Tipo | G10: Categoria | H10: Valor | R10: Total | S10: =SUM(S8:S9) -> 0 | U10: Presentes | W10: =SUMIF($G$11:$G$18,U10,$H$11:$H$18)+SUMIF($G$24:$G$35,U10,$H$24:$H$35)+SUMIF($N$8:$N$35,U10,$P$8:$P$35) -> 0 | X10: =IF($F$4=0,0,W10/$F$4) -> 0 | Z10: =U12 -> Desenvolvimento | AA10: =W12 -> 0
U11: Beleza | W11: =SUMIF($G$11:$G$18,U11,$H$11:$H$18)+SUMIF($G$24:$G$35,U11,$H$24:$H$35)+SUMIF($N$8:$N$35,U11,$P$8:$P$35) -> 0 | X11: =IF($F$4=0,0,W11/$F$4) -> 0 | Z11: =U13 -> Lazer | AA11: =W13 -> 0
R12: Saídas | U12: Desenvolvimento | W12: =SUMIF($G$11:$G$18,U12,$H$11:$H$18)+SUMIF($G$24:$G$35,U12,$H$24:$H$35)+SUMIF($N$8:$N$35,U12,$P$8:$P$35) -> 0 | X12: =IF($F$4=0,0,W12/$F$4) -> 0 | Z12: =U14 -> Eletrônicos | AA12: =W14 -> 0
R13: Débito | S13: =SUMIF($F$11:$F$18,R13,$H$11:$H$18)+SUMIF($F$24:$F$35,R13,$H$24:$H$35)+SUMIF($M$8:$M$35,R13,$P$8:$P$35) -> 0 | U13: Lazer | W13: =SUMIF($G$11:$G$18,U13,$H$11:$H$18)+SUMIF($G$24:$G$35,U13,$H$24:$H$35)+SUMIF($N$8:$N$35,U13,$P$8:$P$35) -> 0 | X13: =IF($F$4=0,0,W13/$F$4) -> 0 | Z13: =U15 -> Assinaturas | AA13: =W15 -> 0
R14: Nubank | S14: =SUMIF($F$11:$F$18,R14,$H$11:$H$18)+SUMIF($F$24:$F$35,R14,$H$24:$H$35)+SUMIF($M$8:$M$35,R14,$P$8:$P$35) -> 0 | U14: Eletrônicos | W14: =SUMIF($G$11:$G$18,U14,$H$11:$H$18)+SUMIF($G$24:$G$35,U14,$H$24:$H$35)+SUMIF($N$8:$N$35,U14,$P$8:$P$35) -> 0 | X14: =IF($F$4=0,0,W14/$F$4) -> 0 | Z14: =U16 -> Uber transporte | AA14: =W16 -> 0
R15: Inter | S15: =SUMIF($F$11:$F$18,R15,$H$11:$H$18)+SUMIF($F$24:$F$35,R15,$H$24:$H$35)+SUMIF($M$8:$M$35,R15,$P$8:$P$35) -> 0 | U15: Assinaturas | W15: =SUMIF($G$11:$G$18,U15,$H$11:$H$18)+SUMIF($G$24:$G$35,U15,$H$24:$H$35)+SUMIF($N$8:$N$35,U15,$P$8:$P$35) -> 0 | X15: =IF($F$4=0,0,W15/$F$4) -> 0 | Z15: =U17 -> iFood/restaurante | AA15: =W17 -> 0
R16: Itaú | S16: =SUMIF($F$11:$F$18,R16,$H$11:$H$18)+SUMIF($F$24:$F$35,R16,$H$24:$H$35)+SUMIF($M$8:$M$35,R16,$P$8:$P$35) -> 0 | U16: Uber transporte | W16: =SUMIF($G$11:$G$18,U16,$H$11:$H$18)+SUMIF($G$24:$G$35,U16,$H$24:$H$35)+SUMIF($N$8:$N$35,U16,$P$8:$P$35) -> 0 | X16: =IF($F$4=0,0,W16/$F$4) -> 0 | Z16: =U18 -> Comida faculdade | AA16: =W18 -> 0
R17: Investimentos | S17: =S23 -> 0 | U17: iFood/restaurante | W17: =SUMIF($G$11:$G$18,U17,$H$11:$H$18)+SUMIF($G$24:$G$35,U17,$H$24:$H$35)+SUMIF($N$8:$N$35,U17,$P$8:$P$35) -> 0 | X17: =IF($F$4=0,0,W17/$F$4) -> 0 | Z17: =U19 -> Contas | AA17: =W19 -> 0
R18: Total | S18: =SUM(S13:S17) -> 0 | U18: Comida faculdade | W18: =SUMIF($G$11:$G$18,U18,$H$11:$H$18)+SUMIF($G$24:$G$35,U18,$H$24:$H$35)+SUMIF($N$8:$N$35,U18,$P$8:$P$35) -> 0 | X18: =IF($F$4=0,0,W18/$F$4) -> 0 | Z18: =U20 -> Outros | AA18: =W20 -> 0
U19: Contas | W19: =SUMIF($G$11:$G$18,U19,$H$11:$H$18)+SUMIF($G$24:$G$35,U19,$H$24:$H$35)+SUMIF($N$8:$N$35,U19,$P$8:$P$35) -> 0 | X19: =IF($F$4=0,0,W19/$F$4) -> 0
B20: Total de Parcelamentos | F20: =SUM(H24:H35) -> 0 | R20: Investimentos | U20: Outros | W20: =SUMIF($G$11:$G$18,U20,$H$11:$H$18)+SUMIF($G$24:$G$35,U20,$H$24:$H$35)+SUMIF($N$8:$N$35,U20,$P$8:$P$35) -> 0 | X20: =IF($F$4=0,0,W20/$F$4) -> 0
R21: Reserva
B22: Parcelamentos | R22: Renda fixa | U22: Gastos por tipo de pagamento
B23: Nome | D23: Parcelas | E23: Data | F23: Tipo | G23: Categoria | H23: Valor | R23: Total | S23: =SUM(S21:S22) -> 0 | U23: Tipo | V23: Valor | W23: Data | X23: Pago?
U24: Débito | V24: =S13 -> 0 | X24: ☐
U25: Nubank | V25: =S14 -> 0 | X25: ☐
U26: Inter | V26: =S15 -> 0 | X26: ☐
U27: Itaú | V27: =S16 -> 0 | X27: ☐
R30: Porcentagem de gastos por categoria

Sheet Maio
B2: Maio | Z2: Categoria | AA2: Valor gasto
R3: Saldo: | S3: =S10-S18 -> 0 | U3: Gastos do mês por categoria: | Z3: =U5 -> Mercado | AA3: =W5 -> 0
B4: Total de gastos: | F4: =F7+F20+N4 -> 0 | J4: Total de Gastos do Mês: | N4: =SUM(P8:P35) -> 0 | U4: Categoria | V4: Valor esperado | W4: Valor gasto | X4: Porcentagem | Z4: =U6 -> Despesas eventuais | AA4: =W6 -> 0
U5: Mercado | W5: =SUMIF($G$11:$G$18,U5,$H$11:$H$18)+SUMIF($G$24:$G$35,U5,$H$24:$H$35)+SUMIF($N$8:$N$35,U5,$P$8:$P$35) -> 0 | X5: =IF($F$4=0,0,W5/$F$4) -> 0 | Z5: =U7 -> Necessidades | AA5: =W7 -> 0
J6: Gastos do Mês | U6: Despesas eventuais | W6: =SUMIF($G$11:$G$18,U6,$H$11:$H$18)+SUMIF($G$24:$G$35,U6,$H$24:$H$35)+SUMIF($N$8:$N$35,U6,$P$8:$P$35) -> 0 | X6: =IF($F$4=0,0,W6/$F$4) -> 0 | Z6: =U8 -> Roupa | AA6: =W8 -> 0
B7: Total de Fixos: | F7: =SUM(H11:H18) -> 0 | J7: Nome | L7: Data | M7: Tipo | N7: Categoria | P7: Valor | R7: Entradas | U7: Necessidades | W7: =SUMIF($G$11:$G$18,U7,$H$11:$H$18)+SUMIF($G$24:$G$35,U7,$H$24:$H$35)+SUMIF($N$8:$N$35,U7,$P$8:$P$35) -> 0 | X7: =IF($F$4=0,0,W7/$F$4) -> 0 | Z7: =U9 -> Saúde | AA7: =W9 -> 0
R8: Salário | U8: Roupa | W8: =SUMIF($G$11:$G$18,U8,$H$11:$H$18)+SUMIF($G$24:$G$35,U8,$H$24:$H$35)+SUMIF($N$8:$N$35,U8,$P$8:$P$35) -> 0 | X8: =IF($F$4=0,0,W8/$F$4) -> 0 | Z8: =U10 -> Presentes | AA8: =W10 -> 0
B9: Fixos | R9: Bônus | U9: Saúde | W9: =SUMIF($G$11:$G$18,U9,$H$11:$H$18)+SUMIF($G$24:$G$35,U9,$H$24:$H$35)+SUMIF($N$8:$N$35,U9,$P$8:$P$35) -> 0 | X9: =IF($F$4=0,0,W9/$F$4) -> 0 | Z9: =U11 -> Beleza | AA9: =W11 -> 0
B10: Nome | D10: Pago? | E10: Data | F10: Tipo | G10: Categoria | H10: Valor | R10: Total | S10: =SUM(S8:S9) -> 0 | U10: Presentes | W10: =SUMIF($G$11:$G$18,U10,$H$11:$H$18)+SUMIF($G$24:$G$35,U10,$H$24:$H$35)+SUMIF($N$8:$N$35,U10,$P$8:$P$35) -> 0 | X10: =IF($F$4=0,0,W10/$F$4) -> 0 | Z10: =U12 -> Desenvolvimento | AA10: =W12 -> 0
U11: Beleza | W11: =SUMIF($G$11:$G$18,U11,$H$11:$H$18)+SUMIF($G$24:$G$35,U11,$H$24:$H$35)+SUMIF($N$8:$N$35,U11,$P$8:$P$35) -> 0 | X11: =IF($F$4=0,0,W11/$F$4) -> 0 | Z11: =U13 -> Lazer | AA11: =W13 -> 0
R12: Saídas | U12: Desenvolvimento | W12: =SUMIF($G$11:$G$18,U12,$H$11:$H$18)+SUMIF($G$24:$G$35,U12,$H$24:$H$35)+SUMIF($N$8:$N$35,U12,$P$8:$P$35) -> 0 | X12: =IF($F$4=0,0,W12/$F$4) -> 0 | Z12: =U14 -> Eletrônicos | AA12: =W14 -> 0
R13: Débito | S13: =SUMIF($F$11:$F$18,R13,$H$11:$H$18)+SUMIF($F$24:$F$35,R13,$H$24:$H$35)+SUMIF($M$8:$M$35,R13,$P$8:$P$35) -> 0 | U13: Lazer | W13: =SUMIF($G$11:$G$18,U13,$H$11:$H$18)+SUMIF($G$24:$G$35,U13,$H$24:$H$35)+SUMIF($N$8:$N$35,U13,$P$8:$P$35) -> 0 | X13: =IF($F$4=0,0,W13/$F$4) -> 0 | Z13: =U15 -> Assinaturas | AA13: =W15 -> 0
R14: Nubank | S14: =SUMIF($F$11:$F$18,R14,$H$11:$H$18)+SUMIF($F$24:$F$35,R14,$H$24:$H$35)+SUMIF($M$8:$M$35,R14,$P$8:$P$35) -> 0 | U14: Eletrônicos | W14: =SUMIF($G$11:$G$18,U14,$H$11:$H$18)+SUMIF($G$24:$G$35,U14,$H$24:$H$35)+SUMIF($N$8:$N$35,U14,$P$8:$P$35) -> 0 | X14: =IF($F$4=0,0,W14/$F$4) -> 0 | Z14: =U16 -> Uber transporte | AA14: =W16 -> 0
R15: Inter | S15: =SUMIF($F$11:$F$18,R15,$H$11:$H$18)+SUMIF($F$24:$F$35,R15,$H$24:$H$35)+SUMIF($M$8:$M$35,R15,$P$8:$P$35) -> 0 | U15: Assinaturas | W15: =SUMIF($G$11:$G$18,U15,$H$11:$H$18)+SUMIF($G$24:$G$35,U15,$H$24:$H$35)+SUMIF($N$8:$N$35,U15,$P$8:$P$35) -> 0 | X15: =IF($F$4=0,0,W15/$F$4) -> 0 | Z15: =U17 -> iFood/restaurante | AA15: =W17 -> 0
R16: Itaú | S16: =SUMIF($F$11:$F$18,R16,$H$11:$H$18)+SUMIF($F$24:$F$35,R16,$H$24:$H$35)+SUMIF($M$8:$M$35,R16,$P$8:$P$35) -> 0 | U16: Uber transporte | W16: =SUMIF($G$11:$G$18,U16,$H$11:$H$18)+SUMIF($G$24:$G$35,U16,$H$24:$H$35)+SUMIF($N$8:$N$35,U16,$P$8:$P$35) -> 0 | X16: =IF($F$4=0,0,W16/$F$4) -> 0 | Z16: =U18 -> Comida faculdade | AA16: =W18 -> 0
R17: Investimentos | S17: =S23 -> 0 | U17: iFood/restaurante | W17: =SUMIF($G$11:$G$18,U17,$H$11:$H$18)+SUMIF($G$24:$G$35,U17,$H$24:$H$35)+SUMIF($N$8:$N$35,U17,$P$8:$P$35) -> 0 | X17: =IF($F$4=0,0,W17/$F$4) -> 0 | Z17: =U19 -> Contas | AA17: =W19 -> 0
R18: Total | S18: =SUM(S13:S17) -> 0 | U18: Comida faculdade | W18: =SUMIF($G$11:$G$18,U18,$H$11:$H$18)+SUMIF($G$24:$G$35,U18,$H$24:$H$35)+SUMIF($N$8:$N$35,U18,$P$8:$P$35) -> 0 | X18: =IF($F$4=0,0,W18/$F$4) -> 0 | Z18: =U20 -> Outros | AA18: =W20 -> 0
U19: Contas | W19: =SUMIF($G$11:$G$18,U19,$H$11:$H$18)+SUMIF($G$24:$G$35,U19,$H$24:$H$35)+SUMIF($N$8:$N$35,U19,$P$8:$P$35) -> 0 | X19: =IF($F$4=0,0,W19/$F$4) -> 0
B20: Total de Parcelamentos | F20: =SUM(H24:H35) -> 0 | R20: Investimentos | U20: Outros | W20: =SUMIF($G$11:$G$18,U20,$H$11:$H$18)+SUMIF($G$24:$G$35,U20,$H$24:$H$35)+SUMIF($N$8:$N$35,U20,$P$8:$P$35) -> 0 | X20: =IF($F$4=0,0,W20/$F$4) -> 0
R21: Reserva
B22: Parcelamentos | R22: Renda fixa | U22: Gastos por tipo de pagamento
B23: Nome | D23: Parcelas | E23: Data | F23: Tipo | G23: Categoria | H23: Valor | R23: Total | S23: =SUM(S21:S22) -> 0 | U23: Tipo | V23: Valor | W23: Data | X23: Pago?
U24: Débito | V24: =S13 -> 0 | X24: ☐
U25: Nubank | V25: =S14 -> 0 | X25: ☐
U26: Inter | V26: =S15 -> 0 | X26: ☐
U27: Itaú | V27: =S16 -> 0 | X27: ☐
R30: Porcentagem de gastos por categoria

Sheet Junho
B2: Junho | Z2: Categoria | AA2: Valor gasto
R3: Saldo: | S3: =S10-S18 -> 0 | U3: Gastos do mês por categoria: | Z3: =U5 -> Mercado | AA3: =W5 -> 0
B4: Total de gastos: | F4: =F7+F20+N4 -> 0 | J4: Total de Gastos do Mês: | N4: =SUM(P8:P35) -> 0 | U4: Categoria | V4: Valor esperado | W4: Valor gasto | X4: Porcentagem | Z4: =U6 -> Despesas eventuais | AA4: =W6 -> 0
U5: Mercado | W5: =SUMIF($G$11:$G$18,U5,$H$11:$H$18)+SUMIF($G$24:$G$35,U5,$H$24:$H$35)+SUMIF($N$8:$N$35,U5,$P$8:$P$35) -> 0 | X5: =IF($F$4=0,0,W5/$F$4) -> 0 | Z5: =U7 -> Necessidades | AA5: =W7 -> 0
J6: Gastos do Mês | U6: Despesas eventuais | W6: =SUMIF($G$11:$G$18,U6,$H$11:$H$18)+SUMIF($G$24:$G$35,U6,$H$24:$H$35)+SUMIF($N$8:$N$35,U6,$P$8:$P$35) -> 0 | X6: =IF($F$4=0,0,W6/$F$4) -> 0 | Z6: =U8 -> Roupa | AA6: =W8 -> 0
B7: Total de Fixos: | F7: =SUM(H11:H18) -> 0 | J7: Nome | L7: Data | M7: Tipo | N7: Categoria | P7: Valor | R7: Entradas | U7: Necessidades | W7: =SUMIF($G$11:$G$18,U7,$H$11:$H$18)+SUMIF($G$24:$G$35,U7,$H$24:$H$35)+SUMIF($N$8:$N$35,U7,$P$8:$P$35) -> 0 | X7: =IF($F$4=0,0,W7/$F$4) -> 0 | Z7: =U9 -> Saúde | AA7: =W9 -> 0
R8: Salário | U8: Roupa | W8: =SUMIF($G$11:$G$18,U8,$H$11:$H$18)+SUMIF($G$24:$G$35,U8,$H$24:$H$35)+SUMIF($N$8:$N$35,U8,$P$8:$P$35) -> 0 | X8: =IF($F$4=0,0,W8/$F$4) -> 0 | Z8: =U10 -> Presentes | AA8: =W10 -> 0
B9: Fixos | R9: Bônus | U9: Saúde | W9: =SUMIF($G$11:$G$18,U9,$H$11:$H$18)+SUMIF($G$24:$G$35,U9,$H$24:$H$35)+SUMIF($N$8:$N$35,U9,$P$8:$P$35) -> 0 | X9: =IF($F$4=0,0,W9/$F$4) -> 0 | Z9: =U11 -> Beleza | AA9: =W11 -> 0
B10: Nome | D10: Pago? | E10: Data | F10: Tipo | G10: Categoria | H10: Valor | R10: Total | S10: =SUM(S8:S9) -> 0 | U10: Presentes | W10: =SUMIF($G$11:$G$18,U10,$H$11:$H$18)+SUMIF($G$24:$G$35,U10,$H$24:$H$35)+SUMIF($N$8:$N$35,U10,$P$8:$P$35) -> 0 | X10: =IF($F$4=0,0,W10/$F$4) -> 0 | Z10: =U12 -> Desenvolvimento | AA10: =W12 -> 0
U11: Beleza | W11: =SUMIF($G$11:$G$18,U11,$H$11:$H$18)+SUMIF($G$24:$G$35,U11,$H$24:$H$35)+SUMIF($N$8:$N$35,U11,$P$8:$P$35) -> 0 | X11: =IF($F$4=0,0,W11/$F$4) -> 0 | Z11: =U13 -> Lazer | AA11: =W13 -> 0
R12: Saídas | U12: Desenvolvimento | W12: =SUMIF($G$11:$G$18,U12,$H$11:$H$18)+SUMIF($G$24:$G$35,U12,$H$24:$H$35)+SUMIF($N$8:$N$35,U12,$P$8:$P$35) -> 0 | X12: =IF($F$4=0,0,W12/$F$4) -> 0 | Z12: =U14 -> Eletrônicos | AA12: =W14 -> 0
R13: Débito | S13: =SUMIF($F$11:$F$18,R13,$H$11:$H$18)+SUMIF($F$24:$F$35,R13,$H$24:$H$35)+SUMIF($M$8:$M$35,R13,$P$8:$P$35) -> 0 | U13: Lazer | W13: =SUMIF($G$11:$G$18,U13,$H$11:$H$18)+SUMIF($G$24:$G$35,U13,$H$24:$H$35)+SUMIF($N$8:$N$35,U13,$P$8:$P$35) -> 0 | X13: =IF($F$4=0,0,W13/$F$4) -> 0 | Z13: =U15 -> Assinaturas | AA13: =W15 -> 0
R14: Nubank | S14: =SUMIF($F$11:$F$18,R14,$H$11:$H$18)+SUMIF($F$24:$F$35,R14,$H$24:$H$35)+SUMIF($M$8:$M$35,R14,$P$8:$P$35) -> 0 | U14: Eletrônicos | W14: =SUMIF($G$11:$G$18,U14,$H$11:$H$18)+SUMIF($G$24:$G$35,U14,$H$24:$H$35)+SUMIF($N$8:$N$35,U14,$P$8:$P$35) -> 0 | X14: =IF($F$4=0,0,W14/$F$4) -> 0 | Z14: =U16 -> Uber transporte | AA14: =W16 -> 0
R15: Inter | S15: =SUMIF($F$11:$F$18,R15,$H$11:$H$18)+SUMIF($F$24:$F$35,R15,$H$24:$H$35)+SUMIF($M$8:$M$35,R15,$P$8:$P$35) -> 0 | U15: Assinaturas | W15: =SUMIF($G$11:$G$18,U15,$H$11:$H$18)+SUMIF($G$24:$G$35,U15,$H$24:$H$35)+SUMIF($N$8:$N$35,U15,$P$8:$P$35) -> 0 | X15: =IF($F$4=0,0,W15/$F$4) -> 0 | Z15: =U17 -> iFood/restaurante | AA15: =W17 -> 0
R16: Itaú | S16: =SUMIF($F$11:$F$18,R16,$H$11:$H$18)+SUMIF($F$24:$F$35,R16,$H$24:$H$35)+SUMIF($M$8:$M$35,R16,$P$8:$P$35) -> 0 | U16: Uber transporte | W16: =SUMIF($G$11:$G$18,U16,$H$11:$H$18)+SUMIF($G$24:$G$35,U16,$H$24:$H$35)+SUMIF($N$8:$N$35,U16,$P$8:$P$35) -> 0 | X16: =IF($F$4=0,0,W16/$F$4) -> 0 | Z16: =U18 -> Comida faculdade | AA16: =W18 -> 0
R17: Investimentos | S17: =S23 -> 0 | U17: iFood/restaurante | W17: =SUMIF($G$11:$G$18,U17,$H$11:$H$18)+SUMIF($G$24:$G$35,U17,$H$24:$H$35)+SUMIF($N$8:$N$35,U17,$P$8:$P$35) -> 0 | X17: =IF($F$4=0,0,W17/$F$4) -> 0 | Z17: =U19 -> Contas | AA17: =W19 -> 0
R18: Total | S18: =SUM(S13:S17) -> 0 | U18: Comida faculdade | W18: =SUMIF($G$11:$G$18,U18,$H$11:$H$18)+SUMIF($G$24:$G$35,U18,$H$24:$H$35)+SUMIF($N$8:$N$35,U18,$P$8:$P$35) -> 0 | X18: =IF($F$4=0,0,W18/$F$4) -> 0 | Z18: =U20 -> Outros | AA18: =W20 -> 0
U19: Contas | W19: =SUMIF($G$11:$G$18,U19,$H$11:$H$18)+SUMIF($G$24:$G$35,U19,$H$24:$H$35)+SUMIF($N$8:$N$35,U19,$P$8:$P$35) -> 0 | X19: =IF($F$4=0,0,W19/$F$4) -> 0
B20: Total de Parcelamentos | F20: =SUM(H24:H35) -> 0 | R20: Investimentos | U20: Outros | W20: =SUMIF($G$11:$G$18,U20,$H$11:$H$18)+SUMIF($G$24:$G$35,U20,$H$24:$H$35)+SUMIF($N$8:$N$35,U20,$P$8:$P$35) -> 0 | X20: =IF($F$4=0,0,W20/$F$4) -> 0
R21: Reserva
B22: Parcelamentos | R22: Renda fixa | U22: Gastos por tipo de pagamento
B23: Nome | D23: Parcelas | E23: Data | F23: Tipo | G23: Categoria | H23: Valor | R23: Total | S23: =SUM(S21:S22) -> 0 | U23: Tipo | V23: Valor | W23: Data | X23: Pago?
U24: Débito | V24: =S13 -> 0 | X24: ☐
U25: Nubank | V25: =S14 -> 0 | X25: ☐
U26: Inter | V26: =S15 -> 0 | X26: ☐
U27: Itaú | V27: =S16 -> 0 | X27: ☐
R30: Porcentagem de gastos por categoria

Sheet Julho
B2: Julho | Z2: Categoria | AA2: Valor gasto
R3: Saldo: | S3: =S10-S18 -> 0 | U3: Gastos do mês por categoria: | Z3: =U5 -> Mercado | AA3: =W5 -> 0
B4: Total de gastos: | F4: =F7+F20+N4 -> 0 | J4: Total de Gastos do Mês: | N4: =SUM(P8:P35) -> 0 | U4: Categoria | V4: Valor esperado | W4: Valor gasto | X4: Porcentagem | Z4: =U6 -> Despesas eventuais | AA4: =W6 -> 0
U5: Mercado | W5: =SUMIF($G$11:$G$18,U5,$H$11:$H$18)+SUMIF($G$24:$G$35,U5,$H$24:$H$35)+SUMIF($N$8:$N$35,U5,$P$8:$P$35) -> 0 | X5: =IF($F$4=0,0,W5/$F$4) -> 0 | Z5: =U7 -> Necessidades | AA5: =W7 -> 0
J6: Gastos do Mês | U6: Despesas eventuais | W6: =SUMIF($G$11:$G$18,U6,$H$11:$H$18)+SUMIF($G$24:$G$35,U6,$H$24:$H$35)+SUMIF($N$8:$N$35,U6,$P$8:$P$35) -> 0 | X6: =IF($F$4=0,0,W6/$F$4) -> 0 | Z6: =U8 -> Roupa | AA6: =W8 -> 0
B7: Total de Fixos: | F7: =SUM(H11:H18) -> 0 | J7: Nome | L7: Data | M7: Tipo | N7: Categoria | P7: Valor | R7: Entradas | U7: Necessidades | W7: =SUMIF($G$11:$G$18,U7,$H$11:$H$18)+SUMIF($G$24:$G$35,U7,$H$24:$H$35)+SUMIF($N$8:$N$35,U7,$P$8:$P$35) -> 0 | X7: =IF($F$4=0,0,W7/$F$4) -> 0 | Z7: =U9 -> Saúde | AA7: =W9 -> 0
R8: Salário | U8: Roupa | W8: =SUMIF($G$11:$G$18,U8,$H$11:$H$18)+SUMIF($G$24:$G$35,U8,$H$24:$H$35)+SUMIF($N$8:$N$35,U8,$P$8:$P$35) -> 0 | X8: =IF($F$4=0,0,W8/$F$4) -> 0 | Z8: =U10 -> Presentes | AA8: =W10 -> 0
B9: Fixos | R9: Bônus | U9: Saúde | W9: =SUMIF($G$11:$G$18,U9,$H$11:$H$18)+SUMIF($G$24:$G$35,U9,$H$24:$H$35)+SUMIF($N$8:$N$35,U9,$P$8:$P$35) -> 0 | X9: =IF($F$4=0,0,W9/$F$4) -> 0 | Z9: =U11 -> Beleza | AA9: =W11 -> 0
B10: Nome | D10: Pago? | E10: Data | F10: Tipo | G10: Categoria | H10: Valor | R10: Total | S10: =SUM(S8:S9) -> 0 | U10: Presentes | W10: =SUMIF($G$11:$G$18,U10,$H$11:$H$18)+SUMIF($G$24:$G$35,U10,$H$24:$H$35)+SUMIF($N$8:$N$35,U10,$P$8:$P$35) -> 0 | X10: =IF($F$4=0,0,W10/$F$4) -> 0 | Z10: =U12 -> Desenvolvimento | AA10: =W12 -> 0
U11: Beleza | W11: =SUMIF($G$11:$G$18,U11,$H$11:$H$18)+SUMIF($G$24:$G$35,U11,$H$24:$H$35)+SUMIF($N$8:$N$35,U11,$P$8:$P$35) -> 0 | X11: =IF($F$4=0,0,W11/$F$4) -> 0 | Z11: =U13 -> Lazer | AA11: =W13 -> 0
R12: Saídas | U12: Desenvolvimento | W12: =SUMIF($G$11:$G$18,U12,$H$11:$H$18)+SUMIF($G$24:$G$35,U12,$H$24:$H$35)+SUMIF($N$8:$N$35,U12,$P$8:$P$35) -> 0 | X12: =IF($F$4=0,0,W12/$F$4) -> 0 | Z12: =U14 -> Eletrônicos | AA12: =W14 -> 0
R13: Débito | S13: =SUMIF($F$11:$F$18,R13,$H$11:$H$18)+SUMIF($F$24:$F$35,R13,$H$24:$H$35)+SUMIF($M$8:$M$35,R13,$P$8:$P$35) -> 0 | U13: Lazer | W13: =SUMIF($G$11:$G$18,U13,$H$11:$H$18)+SUMIF($G$24:$G$35,U13,$H$24:$H$35)+SUMIF($N$8:$N$35,U13,$P$8:$P$35) -> 0 | X13: =IF($F$4=0,0,W13/$F$4) -> 0 | Z13: =U15 -> Assinaturas | AA13: =W15 -> 0
R14: Nubank | S14: =SUMIF($F$11:$F$18,R14,$H$11:$H$18)+SUMIF($F$24:$F$35,R14,$H$24:$H$35)+SUMIF($M$8:$M$35,R14,$P$8:$P$35) -> 0 | U14: Eletrônicos | W14: =SUMIF($G$11:$G$18,U14,$H$11:$H$18)+SUMIF($G$24:$G$35,U14,$H$24:$H$35)+SUMIF($N$8:$N$35,U14,$P$8:$P$35) -> 0 | X14: =IF($F$4=0,0,W14/$F$4) -> 0 | Z14: =U16 -> Uber transporte | AA14: =W16 -> 0
R15: Inter | S15: =SUMIF($F$11:$F$18,R15,$H$11:$H$18)+SUMIF($F$24:$F$35,R15,$H$24:$H$35)+SUMIF($M$8:$M$35,R15,$P$8:$P$35) -> 0 | U15: Assinaturas | W15: =SUMIF($G$11:$G$18,U15,$H$11:$H$18)+SUMIF($G$24:$G$35,U15,$H$24:$H$35)+SUMIF($N$8:$N$35,U15,$P$8:$P$35) -> 0 | X15: =IF($F$4=0,0,W15/$F$4) -> 0 | Z15: =U17 -> iFood/restaurante | AA15: =W17 -> 0
R16: Itaú | S16: =SUMIF($F$11:$F$18,R16,$H$11:$H$18)+SUMIF($F$24:$F$35,R16,$H$24:$H$35)+SUMIF($M$8:$M$35,R16,$P$8:$P$35) -> 0 | U16: Uber transporte | W16: =SUMIF($G$11:$G$18,U16,$H$11:$H$18)+SUMIF($G$24:$G$35,U16,$H$24:$H$35)+SUMIF($N$8:$N$35,U16,$P$8:$P$35) -> 0 | X16: =IF($F$4=0,0,W16/$F$4) -> 0 | Z16: =U18 -> Comida faculdade | AA16: =W18 -> 0
R17: Investimentos | S17: =S23 -> 0 | U17: iFood/restaurante | W17: =SUMIF($G$11:$G$18,U17,$H$11:$H$18)+SUMIF($G$24:$G$35,U17,$H$24:$H$35)+SUMIF($N$8:$N$35,U17,$P$8:$P$35) -> 0 | X17: =IF($F$4=0,0,W17/$F$4) -> 0 | Z17: =U19 -> Contas | AA17: =W19 -> 0
R18: Total | S18: =SUM(S13:S17) -> 0 | U18: Comida faculdade | W18: =SUMIF($G$11:$G$18,U18,$H$11:$H$18)+SUMIF($G$24:$G$35,U18,$H$24:$H$35)+SUMIF($N$8:$N$35,U18,$P$8:$P$35) -> 0 | X18: =IF($F$4=0,0,W18/$F$4) -> 0 | Z18: =U20 -> Outros | AA18: =W20 -> 0
U19: Contas | W19: =SUMIF($G$11:$G$18,U19,$H$11:$H$18)+SUMIF($G$24:$G$35,U19,$H$24:$H$35)+SUMIF($N$8:$N$35,U19,$P$8:$P$35) -> 0 | X19: =IF($F$4=0,0,W19/$F$4) -> 0
B20: Total de Parcelamentos | F20: =SUM(H24:H35) -> 0 | R20: Investimentos | U20: Outros | W20: =SUMIF($G$11:$G$18,U20,$H$11:$H$18)+SUMIF($G$24:$G$35,U20,$H$24:$H$35)+SUMIF($N$8:$N$35,U20,$P$8:$P$35) -> 0 | X20: =IF($F$4=0,0,W20/$F$4) -> 0
R21: Reserva
B22: Parcelamentos | R22: Renda fixa | U22: Gastos por tipo de pagamento
B23: Nome | D23: Parcelas | E23: Data | F23: Tipo | G23: Categoria | H23: Valor | R23: Total | S23: =SUM(S21:S22) -> 0 | U23: Tipo | V23: Valor | W23: Data | X23: Pago?
U24: Débito | V24: =S13 -> 0 | X24: ☐
U25: Nubank | V25: =S14 -> 0 | X25: ☐
U26: Inter | V26: =S15 -> 0 | X26: ☐
U27: Itaú | V27: =S16 -> 0 | X27: ☐
R30: Porcentagem de gastos por categoria

Sheet Agosto
B2: Agosto | Z2: Categoria | AA2: Valor gasto
R3: Saldo: | S3: =S10-S18 -> 184.1 | U3: Gastos do mês por categoria: | Z3: =U5 -> Mercado | AA3: =W5 -> 282
B4: Total de gastos: | F4: =F7+F20+N4 -> 1965.9 | J4: Total de Gastos do Mês: | N4: =SUM(P8:P35) -> 740.5 | U4: Categoria | V4: Valor esperado | W4: Valor gasto | X4: Porcentagem | Z4: =U6 -> Despesas eventuais | AA4: =W6 -> 0
U5: Mercado | V5: 600 | W5: =SUMIF($G$11:$G$18,U5,$H$11:$H$18)+SUMIF($G$24:$G$35,U5,$H$24:$H$35)+SUMIF($N$8:$N$35,U5,$P$8:$P$35) -> 282 | X5: =IF($F$4=0,0,W5/$F$4) -> 0.14344575 | Z5: =U7 -> Necessidades | AA5: =W7 -> 58
J6: Gastos do Mês | U6: Despesas eventuais | W6: =SUMIF($G$11:$G$18,U6,$H$11:$H$18)+SUMIF($G$24:$G$35,U6,$H$24:$H$35)+SUMIF($N$8:$N$35,U6,$P$8:$P$35) -> 0 | X6: =IF($F$4=0,0,W6/$F$4) -> 0 | Z6: =U8 -> Roupa | AA6: =W8 -> 248.5
B7: Total de Fixos: | F7: =SUM(H11:H18) -> 608.9 | J7: Nome | L7: Data | M7: Tipo | N7: Categoria | P7: Valor | R7: Entradas | U7: Necessidades | W7: =SUMIF($G$11:$G$18,U7,$H$11:$H$18)+SUMIF($G$24:$G$35,U7,$H$24:$H$35)+SUMIF($N$8:$N$35,U7,$P$8:$P$35) -> 58 | X7: =IF($F$4=0,0,W7/$F$4) -> 0.029503027 | Z7: =U9 -> Saúde | AA7: =W9 -> 158
J8: Mercado | L8: 46235 | M8: Nubank | N8: Mercado | P8: 125 | R8: Salário | S8: 2400 | U8: Roupa | V8: 100 | W8: =SUMIF($G$11:$G$18,U8,$H$11:$H$18)+SUMIF($G$24:$G$35,U8,$H$24:$H$35)+SUMIF($N$8:$N$35,U8,$P$8:$P$35) -> 248.5 | X8: =IF($F$4=0,0,W8/$F$4) -> 0.12640521 | Z8: =U10 -> Presentes | AA8: =W10 -> 0
B9: Fixos | J9: Uber | L9: 46235 | M9: Nubank | N9: Uber transporte | P9: 31 | R9: Bônus | U9: Saúde | W9: =SUMIF($G$11:$G$18,U9,$H$11:$H$18)+SUMIF($G$24:$G$35,U9,$H$24:$H$35)+SUMIF($N$8:$N$35,U9,$P$8:$P$35) -> 158 | X9: =IF($F$4=0,0,W9/$F$4) -> 0.080370314 | Z9: =U11 -> Beleza | AA9: =W11 -> 332
B10: Nome | D10: Pago? | E10: Data | F10: Tipo | G10: Categoria | H10: Valor | J10: Uber | L10: 46235 | M10: Nubank | N10: Uber transporte | P10: 25 | R10: Total | S10: =SUM(S8:S9) -> 2400 | U10: Presentes | W10: =SUMIF($G$11:$G$18,U10,$H$11:$H$18)+SUMIF($G$24:$G$35,U10,$H$24:$H$35)+SUMIF($N$8:$N$35,U10,$P$8:$P$35) -> 0 | X10: =IF($F$4=0,0,W10/$F$4) -> 0 | Z10: =U12 -> Desenvolvimento | AA10: =W12 -> 0
B11: Academia | D11: ☐ | E11: 46239 | F11: Nubank | G11: Saúde | H11: 120 | J11: Hambúrguer jantar | L11: 46236 | M11: Nubank | N11: iFood/restaurante | P11: 39 | U11: Beleza | V11: 100 | W11: =SUMIF($G$11:$G$18,U11,$H$11:$H$18)+SUMIF($G$24:$G$35,U11,$H$24:$H$35)+SUMIF($N$8:$N$35,U11,$P$8:$P$35) -> 332 | X11: =IF($F$4=0,0,W11/$F$4) -> 0.16887939 | Z11: =U13 -> Lazer | AA11: =W13 -> 0
B12: Conta de água | D12: ☐ | E12: 46240 | F12: Nubank | G12: Contas | H12: 120 | J12: Almoço trabalho | L12: 46236 | M12: Nubank | N12: iFood/restaurante | P12: 35 | R12: Saídas | U12: Desenvolvimento | W12: =SUMIF($G$11:$G$18,U12,$H$11:$H$18)+SUMIF($G$24:$G$35,U12,$H$24:$H$35)+SUMIF($N$8:$N$35,U12,$P$8:$P$35) -> 0 | X12: =IF($F$4=0,0,W12/$F$4) -> 0 | Z12: =U14 -> Eletrônicos | AA12: =W14 -> 45
B13: Internet | D13: ☐ | E13: 46241 | F13: Nubank | G13: Contas | H13: 130 | J13: Farmácia | L13: 46237 | M13: Nubank | N13: Beleza | P13: 47 | R13: Débito | S13: =SUMIF($F$11:$F$18,R13,$H$11:$H$18)+SUMIF($F$24:$F$35,R13,$H$24:$H$35)+SUMIF($M$8:$M$35,R13,$P$8:$P$35) -> 96.9 | U13: Lazer | W13: =SUMIF($G$11:$G$18,U13,$H$11:$H$18)+SUMIF($G$24:$G$35,U13,$H$24:$H$35)+SUMIF($N$8:$N$35,U13,$P$8:$P$35) -> 0 | X13: =IF($F$4=0,0,W13/$F$4) -> 0 | Z13: =U15 -> Assinaturas | AA13: =W15 -> 103.9
B14: Amazon Prime | D14: ☐ | E14: 46242 | F14: Débito | G14: Assinaturas | H14: 11.9 | J14: Café faculdade | L14: 46239 | M14: Inter | N14: Comida faculdade | P14: 15 | R14: Nubank | S14: =SUMIF($F$11:$F$18,R14,$H$11:$H$18)+SUMIF($F$24:$F$35,R14,$H$24:$H$35)+SUMIF($M$8:$M$35,R14,$P$8:$P$35) -> 1417.5 | U14: Eletrônicos | W14: =SUMIF($G$11:$G$18,U14,$H$11:$H$18)+SUMIF($G$24:$G$35,U14,$H$24:$H$35)+SUMIF($N$8:$N$35,U14,$P$8:$P$35) -> 45 | X14: =IF($F$4=0,0,W14/$F$4) -> 0.022890279 | Z14: =U16 -> Uber transporte | AA14: =W16 -> 83
B15: iCloud | D15: ☐ | E15: 46243 | F15: Nubank | G15: Assinaturas | H15: 55 | J15: Frutas | L15: 46239 | M15: Nubank | N15: Mercado | P15: 34 | R15: Inter | S15: =SUMIF($F$11:$F$18,R15,$H$11:$H$18)+SUMIF($F$24:$F$35,R15,$H$24:$H$35)+SUMIF($M$8:$M$35,R15,$P$8:$P$35) -> 289.5 | U15: Assinaturas | W15: =SUMIF($G$11:$G$18,U15,$H$11:$H$18)+SUMIF($G$24:$G$35,U15,$H$24:$H$35)+SUMIF($N$8:$N$35,U15,$P$8:$P$35) -> 103.9 | X15: =IF($F$4=0,0,W15/$F$4) -> 0.052851111 | Z15: =U17 -> iFood/restaurante | AA15: =W17 -> 222.5
B16: Conta de luz | D16: ☐ | E16: 46244 | F16: Nubank | G16: Contas | H16: 135 | J16: Adicional Claro | L16: 46240 | M16: Débito | N16: Necessidades | P16: 20 | R16: Itaú | S16: =SUMIF($F$11:$F$18,R16,$H$11:$H$18)+SUMIF($F$24:$F$35,R16,$H$24:$H$35)+SUMIF($M$8:$M$35,R16,$P$8:$P$35) -> 162 | U16: Uber transporte | V16: 150 | W16: =SUMIF($G$11:$G$18,U16,$H$11:$H$18)+SUMIF($G$24:$G$35,U16,$H$24:$H$35)+SUMIF($N$8:$N$35,U16,$P$8:$P$35) -> 83 | X16: =IF($F$4=0,0,W16/$F$4) -> 0.042219848 | Z16: =U18 -> Comida faculdade | AA16: =W18 -> 48
B17: Spotify | D17: ☐ | E17: 46244 | F17: Nubank | G17: Assinaturas | H17: 12 | J17: iFood jantar | L17: 46240 | M17: Nubank | N17: iFood/restaurante | P17: 42 | R17: Investimentos | S17: =S23 -> 250 | U17: iFood/restaurante | V17: 150 | W17: =SUMIF($G$11:$G$18,U17,$H$11:$H$18)+SUMIF($G$24:$G$35,U17,$H$24:$H$35)+SUMIF($N$8:$N$35,U17,$P$8:$P$35) -> 222.5 | X17: =IF($F$4=0,0,W17/$F$4) -> 0.11317971 | Z17: =U19 -> Contas | AA17: =W19 -> 385
B18: Reservatório de Dopamina | D18: ☐ | E18: 46246 | F18: Nubank | G18: Assinaturas | H18: 25 | J18: Uber trabalho | L18: 46241 | M18: Nubank | N18: Uber transporte | P18: 27 | R18: Total | S18: =SUM(S13:S17) -> 2215.9 | U18: Comida faculdade | V18: 40 | W18: =SUMIF($G$11:$G$18,U18,$H$11:$H$18)+SUMIF($G$24:$G$35,U18,$H$24:$H$35)+SUMIF($N$8:$N$35,U18,$P$8:$P$35) -> 48 | X18: =IF($F$4=0,0,W18/$F$4) -> 0.024416298 | Z18: =U20 -> Outros | AA18: =W20 -> 0
J19: Café faculdade | L19: 46242 | M19: Nubank | N19: Comida faculdade | P19: 10 | U19: Contas | W19: =SUMIF($G$11:$G$18,U19,$H$11:$H$18)+SUMIF($G$24:$G$35,U19,$H$24:$H$35)+SUMIF($N$8:$N$35,U19,$P$8:$P$35) -> 385 | X19: =IF($F$4=0,0,W19/$F$4) -> 0.19583906
B20: Total de Parcelamentos | F20: =SUM(H24:H35) -> 616.5 | J20: Mercado | L20: 46243 | M20: Nubank | N20: Mercado | P20: 65 | R20: Investimentos | U20: Outros | W20: =SUMIF($G$11:$G$18,U20,$H$11:$H$18)+SUMIF($G$24:$G$35,U20,$H$24:$H$35)+SUMIF($N$8:$N$35,U20,$P$8:$P$35) -> 0 | X20: =IF($F$4=0,0,W20/$F$4) -> 0
J21: Jantar poke | L21: 46244 | M21: Débito | N21: iFood/restaurante | P21: 65 | R21: Reserva | S21: 150
B22: Parcelamentos | J22: Restrição alérgica | L22: 46245 | M22: Nubank | N22: Saúde | P22: 38 | R22: Renda fixa | S22: 100 | U22: Gastos por tipo de pagamento
B23: Nome | D23: Parcelas | E23: Data | F23: Tipo | G23: Categoria | H23: Valor | J23: Café faculdade | L23: 46246 | M23: Nubank | N23: Comida faculdade | P23: 8 | R23: Total | S23: =SUM(S21:S22) -> 250 | U23: Tipo | V23: Valor | W23: Data | X23: Pago?
B24: Depilação a laser | D24: 5/12 | E24: 46137 | F24: Nubank | G24: Beleza | H24: 105 | J24: Mercado | L24: 46247 | M24: Nubank | N24: Mercado | P24: 58 | U24: Débito | V24: =S13 -> 96.9 | W24: 46266 | X24: ☐
B25: Fone de ouvido | D25: 5/5 | E25: 46124 | F25: Itaú | G25: Eletrônicos | H25: 45 | J25: Almoço delivery | L25: 46249 | M25: Nubank | N25: iFood/restaurante | P25: 41.5 | U25: Nubank | V25: =S14 -> 1417.5 | W25: 46267 | X25: ☐
B26: Roupa de treino | D26: 4/4 | E26: 46167 | F26: Nubank | G26: Roupa | H26: 37 | J26: Pão e café | L26: 46250 | M26: Nubank | N26: Comida faculdade | P26: 15 | U26: Inter | V26: =S15 -> 289.5 | W26: 46268 | X26: ☐
B27: Maquiagem Oceane | D27: 3/3 | E27: 46190 | F27: Itaú | G27: Beleza | H27: 42 | U27: Itaú | V27: =S16 -> 162 | W27: 46269 | X27: ☐
B28: Escova de cabelo | D28: 2/2 | E28: 46206 | F28: Inter | G28: Beleza | H28: 63
B29: Vestido | D29: 2/3 | E29: 46211 | F29: Inter | G29: Roupa | H29: 69
B30: Blush Sheglam | D30: 2/3 | E30: 46212 | F30: Itaú | G30: Beleza | H30: 75 | R30: Porcentagem de gastos por categoria
B31: Tênis esporte | D31: 2/6 | E31: 46213 | F31: Inter | G31: Roupa | H31: 75
B32: Roupa viagem | D32: 2/3 | E32: 46213 | F32: Inter | G32: Roupa | H32: 67.5
B33: Itens Shopee | D33: 1/3 | E33: 46215 | F33: Nubank | G33: Necessidades | H33: 38

Sheet Setembro
B2: Setembro | Z2: Categoria | AA2: Valor gasto
R3: Saldo: | S3: =S10-S18 -> 1400 | U3: Gastos do mês por categoria: | Z3: =U5 -> Mercado | AA3: =W5 -> 0
B4: Total de gastos: | F4: =F7+F20+N4 -> 300 | J4: Total de Gastos do Mês: | N4: =SUM(P8:P35) -> 0 | U4: Categoria | V4: Valor esperado | W4: Valor gasto | X4: Porcentagem | Z4: =U6 -> Despesas eventuais | AA4: =W6 -> 0
U5: Mercado | W5: =SUMIF($G$11:$G$18,U5,$H$11:$H$18)+SUMIF($G$24:$G$35,U5,$H$24:$H$35)+SUMIF($N$8:$N$35,U5,$P$8:$P$35) -> 0 | X5: =IF($F$4=0,0,W5/$F$4) -> 0 | Z5: =U7 -> Necessidades | AA5: =W7 -> 130
J6: Gastos do Mês | U6: Despesas eventuais | W6: =SUMIF($G$11:$G$18,U6,$H$11:$H$18)+SUMIF($G$24:$G$35,U6,$H$24:$H$35)+SUMIF($N$8:$N$35,U6,$P$8:$P$35) -> 0 | X6: =IF($F$4=0,0,W6/$F$4) -> 0 | Z6: =U8 -> Roupa | AA6: =W8 -> 0
B7: Total de Fixos: | F7: =SUM(H11:H18) -> 300 | J7: Nome | L7: Data | M7: Tipo | N7: Categoria | P7: Valor | R7: Entradas | U7: Necessidades | W7: =SUMIF($G$11:$G$18,U7,$H$11:$H$18)+SUMIF($G$24:$G$35,U7,$H$24:$H$35)+SUMIF($N$8:$N$35,U7,$P$8:$P$35) -> 130 | X7: =IF($F$4=0,0,W7/$F$4) -> 0.43333333 | Z7: =U9 -> Saúde | AA7: =W9 -> 0
R8: Salário | S8: 2500 | U8: Roupa | W8: =SUMIF($G$11:$G$18,U8,$H$11:$H$18)+SUMIF($G$24:$G$35,U8,$H$24:$H$35)+SUMIF($N$8:$N$35,U8,$P$8:$P$35) -> 0 | X8: =IF($F$4=0,0,W8/$F$4) -> 0 | Z8: =U10 -> Presentes | AA8: =W10 -> 0
B9: Fixos | R9: Bônus | S9: 0 | U9: Saúde | W9: =SUMIF($G$11:$G$18,U9,$H$11:$H$18)+SUMIF($G$24:$G$35,U9,$H$24:$H$35)+SUMIF($N$8:$N$35,U9,$P$8:$P$35) -> 0 | X9: =IF($F$4=0,0,W9/$F$4) -> 0 | Z9: =U11 -> Beleza | AA9: =W11 -> 0
B10: Nome | D10: Pago? | E10: Data | F10: Tipo | G10: Categoria | H10: Valor | R10: Total | S10: =SUM(S8:S9) -> 2500 | U10: Presentes | W10: =SUMIF($G$11:$G$18,U10,$H$11:$H$18)+SUMIF($G$24:$G$35,U10,$H$24:$H$35)+SUMIF($N$8:$N$35,U10,$P$8:$P$35) -> 0 | X10: =IF($F$4=0,0,W10/$F$4) -> 0 | Z10: =U12 -> Desenvolvimento | AA10: =W12 -> 170
B11: Internet | D11: ☐ | E11: 46249 | F11: Débito | G11: Necessidades | H11: 130 | U11: Beleza | W11: =SUMIF($G$11:$G$18,U11,$H$11:$H$18)+SUMIF($G$24:$G$35,U11,$H$24:$H$35)+SUMIF($N$8:$N$35,U11,$P$8:$P$35) -> 0 | X11: =IF($F$4=0,0,W11/$F$4) -> 0 | Z11: =U13 -> Lazer | AA11: =W13 -> 0
B12: Faculdade | D12: ☐ | E12: 46259 | F12: Débito | G12: Desenvolvimento | H12: 170 | R12: Saídas | U12: Desenvolvimento | W12: =SUMIF($G$11:$G$18,U12,$H$11:$H$18)+SUMIF($G$24:$G$35,U12,$H$24:$H$35)+SUMIF($N$8:$N$35,U12,$P$8:$P$35) -> 170 | X12: =IF($F$4=0,0,W12/$F$4) -> 0.56666667 | Z12: =U14 -> Eletrônicos | AA12: =W14 -> 0
B13: Fatura Cartão | D13: ☐ | E13: 11 | R13: Débito | S13: =SUMIF($F$11:$F$18,R13,$H$11:$H$18)+SUMIF($F$24:$F$35,R13,$H$24:$H$35)+SUMIF($M$8:$M$35,R13,$P$8:$P$35) -> 300 | U13: Lazer | W13: =SUMIF($G$11:$G$18,U13,$H$11:$H$18)+SUMIF($G$24:$G$35,U13,$H$24:$H$35)+SUMIF($N$8:$N$35,U13,$P$8:$P$35) -> 0 | X13: =IF($F$4=0,0,W13/$F$4) -> 0 | Z13: =U15 -> Assinaturas | AA13: =W15 -> 0
R14: Nubank | S14: =SUMIF($F$11:$F$18,R14,$H$11:$H$18)+SUMIF($F$24:$F$35,R14,$H$24:$H$35)+SUMIF($M$8:$M$35,R14,$P$8:$P$35) -> 0 | U14: Eletrônicos | W14: =SUMIF($G$11:$G$18,U14,$H$11:$H$18)+SUMIF($G$24:$G$35,U14,$H$24:$H$35)+SUMIF($N$8:$N$35,U14,$P$8:$P$35) -> 0 | X14: =IF($F$4=0,0,W14/$F$4) -> 0 | Z14: =U16 -> Uber transporte | AA14: =W16 -> 0
R15: Inter | S15: =SUMIF($F$11:$F$18,R15,$H$11:$H$18)+SUMIF($F$24:$F$35,R15,$H$24:$H$35)+SUMIF($M$8:$M$35,R15,$P$8:$P$35) -> 0 | U15: Assinaturas | W15: =SUMIF($G$11:$G$18,U15,$H$11:$H$18)+SUMIF($G$24:$G$35,U15,$H$24:$H$35)+SUMIF($N$8:$N$35,U15,$P$8:$P$35) -> 0 | X15: =IF($F$4=0,0,W15/$F$4) -> 0 | Z15: =U17 -> iFood/restaurante | AA15: =W17 -> 0
R16: Itaú | S16: =SUMIF($F$11:$F$18,R16,$H$11:$H$18)+SUMIF($F$24:$F$35,R16,$H$24:$H$35)+SUMIF($M$8:$M$35,R16,$P$8:$P$35) -> 0 | U16: Uber transporte | W16: =SUMIF($G$11:$G$18,U16,$H$11:$H$18)+SUMIF($G$24:$G$35,U16,$H$24:$H$35)+SUMIF($N$8:$N$35,U16,$P$8:$P$35) -> 0 | X16: =IF($F$4=0,0,W16/$F$4) -> 0 | Z16: =U18 -> Comida faculdade | AA16: =W18 -> 0
R17: Investimentos | S17: =S23 -> 800 | U17: iFood/restaurante | W17: =SUMIF($G$11:$G$18,U17,$H$11:$H$18)+SUMIF($G$24:$G$35,U17,$H$24:$H$35)+SUMIF($N$8:$N$35,U17,$P$8:$P$35) -> 0 | X17: =IF($F$4=0,0,W17/$F$4) -> 0 | Z17: =U19 -> Contas | AA17: =W19 -> 0
R18: Total | S18: =SUM(S13:S17) -> 1100 | U18: Comida faculdade | W18: =SUMIF($G$11:$G$18,U18,$H$11:$H$18)+SUMIF($G$24:$G$35,U18,$H$24:$H$35)+SUMIF($N$8:$N$35,U18,$P$8:$P$35) -> 0 | X18: =IF($F$4=0,0,W18/$F$4) -> 0 | Z18: =U20 -> Outros | AA18: =W20 -> 0
U19: Contas | W19: =SUMIF($G$11:$G$18,U19,$H$11:$H$18)+SUMIF($G$24:$G$35,U19,$H$24:$H$35)+SUMIF($N$8:$N$35,U19,$P$8:$P$35) -> 0 | X19: =IF($F$4=0,0,W19/$F$4) -> 0
B20: Total de Parcelamentos | F20: =SUM(H24:H35) -> 0 | R20: Investimentos | U20: Outros | W20: =SUMIF($G$11:$G$18,U20,$H$11:$H$18)+SUMIF($G$24:$G$35,U20,$H$24:$H$35)+SUMIF($N$8:$N$35,U20,$P$8:$P$35) -> 0 | X20: =IF($F$4=0,0,W20/$F$4) -> 0
R21: Reserva | S21: 800
B22: Parcelamentos | R22: Renda fixa | U22: Gastos por tipo de pagamento
B23: Nome | D23: Parcelas | E23: Data | F23: Tipo | G23: Categoria | H23: Valor | R23: Total | S23: =SUM(S21:S22) -> 800 | U23: Tipo | V23: Valor | W23: Data | X23: Pago?
U24: Débito | V24: =S13 -> 300 | X24: ☐
U25: Nubank | V25: =S14 -> 0 | X25: ☐
U26: Inter | V26: =S15 -> 0 | X26: ☐
U27: Itaú | V27: =S16 -> 0 | X27: ☐
R30: Porcentagem de gastos por categoria

Sheet Outubro
B2: Outubro | Z2: Categoria | AA2: Valor gasto
R3: Saldo: | S3: =S10-S18 -> 0 | U3: Gastos do mês por categoria: | Z3: =U5 -> Mercado | AA3: =W5 -> 0
B4: Total de gastos: | F4: =F7+F20+N4 -> 0 | J4: Total de Gastos do Mês: | N4: =SUM(P8:P35) -> 0 | U4: Categoria | V4: Valor esperado | W4: Valor gasto | X4: Porcentagem | Z4: =U6 -> Despesas eventuais | AA4: =W6 -> 0
U5: Mercado | W5: =SUMIF($G$11:$G$18,U5,$H$11:$H$18)+SUMIF($G$24:$G$35,U5,$H$24:$H$35)+SUMIF($N$8:$N$35,U5,$P$8:$P$35) -> 0 | X5: =IF($F$4=0,0,W5/$F$4) -> 0 | Z5: =U7 -> Necessidades | AA5: =W7 -> 0
J6: Gastos do Mês | U6: Despesas eventuais | W6: =SUMIF($G$11:$G$18,U6,$H$11:$H$18)+SUMIF($G$24:$G$35,U6,$H$24:$H$35)+SUMIF($N$8:$N$35,U6,$P$8:$P$35) -> 0 | X6: =IF($F$4=0,0,W6/$F$4) -> 0 | Z6: =U8 -> Roupa | AA6: =W8 -> 0
B7: Total de Fixos: | F7: =SUM(H11:H18) -> 0 | J7: Nome | L7: Data | M7: Tipo | N7: Categoria | P7: Valor | R7: Entradas | U7: Necessidades | W7: =SUMIF($G$11:$G$18,U7,$H$11:$H$18)+SUMIF($G$24:$G$35,U7,$H$24:$H$35)+SUMIF($N$8:$N$35,U7,$P$8:$P$35) -> 0 | X7: =IF($F$4=0,0,W7/$F$4) -> 0 | Z7: =U9 -> Saúde | AA7: =W9 -> 0
R8: Salário | U8: Roupa | W8: =SUMIF($G$11:$G$18,U8,$H$11:$H$18)+SUMIF($G$24:$G$35,U8,$H$24:$H$35)+SUMIF($N$8:$N$35,U8,$P$8:$P$35) -> 0 | X8: =IF($F$4=0,0,W8/$F$4) -> 0 | Z8: =U10 -> Presentes | AA8: =W10 -> 0
B9: Fixos | R9: Bônus | U9: Saúde | W9: =SUMIF($G$11:$G$18,U9,$H$11:$H$18)+SUMIF($G$24:$G$35,U9,$H$24:$H$35)+SUMIF($N$8:$N$35,U9,$P$8:$P$35) -> 0 | X9: =IF($F$4=0,0,W9/$F$4) -> 0 | Z9: =U11 -> Beleza | AA9: =W11 -> 0
B10: Nome | D10: Pago? | E10: Data | F10: Tipo | G10: Categoria | H10: Valor | R10: Total | S10: =SUM(S8:S9) -> 0 | U10: Presentes | W10: =SUMIF($G$11:$G$18,U10,$H$11:$H$18)+SUMIF($G$24:$G$35,U10,$H$24:$H$35)+SUMIF($N$8:$N$35,U10,$P$8:$P$35) -> 0 | X10: =IF($F$4=0,0,W10/$F$4) -> 0 | Z10: =U12 -> Desenvolvimento | AA10: =W12 -> 0
U11: Beleza | W11: =SUMIF($G$11:$G$18,U11,$H$11:$H$18)+SUMIF($G$24:$G$35,U11,$H$24:$H$35)+SUMIF($N$8:$N$35,U11,$P$8:$P$35) -> 0 | X11: =IF($F$4=0,0,W11/$F$4) -> 0 | Z11: =U13 -> Lazer | AA11: =W13 -> 0
R12: Saídas | U12: Desenvolvimento | W12: =SUMIF($G$11:$G$18,U12,$H$11:$H$18)+SUMIF($G$24:$G$35,U12,$H$24:$H$35)+SUMIF($N$8:$N$35,U12,$P$8:$P$35) -> 0 | X12: =IF($F$4=0,0,W12/$F$4) -> 0 | Z12: =U14 -> Eletrônicos | AA12: =W14 -> 0
R13: Débito | S13: =SUMIF($F$11:$F$18,R13,$H$11:$H$18)+SUMIF($F$24:$F$35,R13,$H$24:$H$35)+SUMIF($M$8:$M$35,R13,$P$8:$P$35) -> 0 | U13: Lazer | W13: =SUMIF($G$11:$G$18,U13,$H$11:$H$18)+SUMIF($G$24:$G$35,U13,$H$24:$H$35)+SUMIF($N$8:$N$35,U13,$P$8:$P$35) -> 0 | X13: =IF($F$4=0,0,W13/$F$4) -> 0 | Z13: =U15 -> Assinaturas | AA13: =W15 -> 0
R14: Nubank | S14: =SUMIF($F$11:$F$18,R14,$H$11:$H$18)+SUMIF($F$24:$F$35,R14,$H$24:$H$35)+SUMIF($M$8:$M$35,R14,$P$8:$P$35) -> 0 | U14: Eletrônicos | W14: =SUMIF($G$11:$G$18,U14,$H$11:$H$18)+SUMIF($G$24:$G$35,U14,$H$24:$H$35)+SUMIF($N$8:$N$35,U14,$P$8:$P$35) -> 0 | X14: =IF($F$4=0,0,W14/$F$4) -> 0 | Z14: =U16 -> Uber transporte | AA14: =W16 -> 0
R15: Inter | S15: =SUMIF($F$11:$F$18,R15,$H$11:$H$18)+SUMIF($F$24:$F$35,R15,$H$24:$H$35)+SUMIF($M$8:$M$35,R15,$P$8:$P$35) -> 0 | U15: Assinaturas | W15: =SUMIF($G$11:$G$18,U15,$H$11:$H$18)+SUMIF($G$24:$G$35,U15,$H$24:$H$35)+SUMIF($N$8:$N$35,U15,$P$8:$P$35) -> 0 | X15: =IF($F$4=0,0,W15/$F$4) -> 0 | Z15: =U17 -> iFood/restaurante | AA15: =W17 -> 0
R16: Itaú | S16: =SUMIF($F$11:$F$18,R16,$H$11:$H$18)+SUMIF($F$24:$F$35,R16,$H$24:$H$35)+SUMIF($M$8:$M$35,R16,$P$8:$P$35) -> 0 | U16: Uber transporte | W16: =SUMIF($G$11:$G$18,U16,$H$11:$H$18)+SUMIF($G$24:$G$35,U16,$H$24:$H$35)+SUMIF($N$8:$N$35,U16,$P$8:$P$35) -> 0 | X16: =IF($F$4=0,0,W16/$F$4) -> 0 | Z16: =U18 -> Comida faculdade | AA16: =W18 -> 0
R17: Investimentos | S17: =S23 -> 0 | U17: iFood/restaurante | W17: =SUMIF($G$11:$G$18,U17,$H$11:$H$18)+SUMIF($G$24:$G$35,U17,$H$24:$H$35)+SUMIF($N$8:$N$35,U17,$P$8:$P$35) -> 0 | X17: =IF($F$4=0,0,W17/$F$4) -> 0 | Z17: =U19 -> Contas | AA17: =W19 -> 0
R18: Total | S18: =SUM(S13:S17) -> 0 | U18: Comida faculdade | W18: =SUMIF($G$11:$G$18,U18,$H$11:$H$18)+SUMIF($G$24:$G$35,U18,$H$24:$H$35)+SUMIF($N$8:$N$35,U18,$P$8:$P$35) -> 0 | X18: =IF($F$4=0,0,W18/$F$4) -> 0 | Z18: =U20 -> Outros | AA18: =W20 -> 0
U19: Contas | W19: =SUMIF($G$11:$G$18,U19,$H$11:$H$18)+SUMIF($G$24:$G$35,U19,$H$24:$H$35)+SUMIF($N$8:$N$35,U19,$P$8:$P$35) -> 0 | X19: =IF($F$4=0,0,W19/$F$4) -> 0
B20: Total de Parcelamentos | F20: =SUM(H24:H35) -> 0 | R20: Investimentos | U20: Outros | W20: =SUMIF($G$11:$G$18,U20,$H$11:$H$18)+SUMIF($G$24:$G$35,U20,$H$24:$H$35)+SUMIF($N$8:$N$35,U20,$P$8:$P$35) -> 0 | X20: =IF($F$4=0,0,W20/$F$4) -> 0
R21: Reserva
B22: Parcelamentos | R22: Renda fixa | U22: Gastos por tipo de pagamento
B23: Nome | D23: Parcelas | E23: Data | F23: Tipo | G23: Categoria | H23: Valor | R23: Total | S23: =SUM(S21:S22) -> 0 | U23: Tipo | V23: Valor | W23: Data | X23: Pago?
U24: Débito | V24: =S13 -> 0 | X24: ☐
U25: Nubank | V25: =S14 -> 0 | X25: ☐
U26: Inter | V26: =S15 -> 0 | X26: ☐
U27: Itaú | V27: =S16 -> 0 | X27: ☐
R30: Porcentagem de gastos por categoria

Sheet Novembro
B2: Novembro | Z2: Categoria | AA2: Valor gasto
R3: Saldo: | S3: =S10-S18 -> 0 | U3: Gastos do mês por categoria: | Z3: =U5 -> Mercado | AA3: =W5 -> 0
B4: Total de gastos: | F4: =F7+F20+N4 -> 0 | J4: Total de Gastos do Mês: | N4: =SUM(P8:P35) -> 0 | U4: Categoria | V4: Valor esperado | W4: Valor gasto | X4: Porcentagem | Z4: =U6 -> Despesas eventuais | AA4: =W6 -> 0
U5: Mercado | W5: =SUMIF($G$11:$G$18,U5,$H$11:$H$18)+SUMIF($G$24:$G$35,U5,$H$24:$H$35)+SUMIF($N$8:$N$35,U5,$P$8:$P$35) -> 0 | X5: =IF($F$4=0,0,W5/$F$4) -> 0 | Z5: =U7 -> Necessidades | AA5: =W7 -> 0
J6: Gastos do Mês | U6: Despesas eventuais | W6: =SUMIF($G$11:$G$18,U6,$H$11:$H$18)+SUMIF($G$24:$G$35,U6,$H$24:$H$35)+SUMIF($N$8:$N$35,U6,$P$8:$P$35) -> 0 | X6: =IF($F$4=0,0,W6/$F$4) -> 0 | Z6: =U8 -> Roupa | AA6: =W8 -> 0
B7: Total de Fixos: | F7: =SUM(H11:H18) -> 0 | J7: Nome | L7: Data | M7: Tipo | N7: Categoria | P7: Valor | R7: Entradas | U7: Necessidades | W7: =SUMIF($G$11:$G$18,U7,$H$11:$H$18)+SUMIF($G$24:$G$35,U7,$H$24:$H$35)+SUMIF($N$8:$N$35,U7,$P$8:$P$35) -> 0 | X7: =IF($F$4=0,0,W7/$F$4) -> 0 | Z7: =U9 -> Saúde | AA7: =W9 -> 0
R8: Salário | U8: Roupa | W8: =SUMIF($G$11:$G$18,U8,$H$11:$H$18)+SUMIF($G$24:$G$35,U8,$H$24:$H$35)+SUMIF($N$8:$N$35,U8,$P$8:$P$35) -> 0 | X8: =IF($F$4=0,0,W8/$F$4) -> 0 | Z8: =U10 -> Presentes | AA8: =W10 -> 0
B9: Fixos | R9: Bônus | U9: Saúde | W9: =SUMIF($G$11:$G$18,U9,$H$11:$H$18)+SUMIF($G$24:$G$35,U9,$H$24:$H$35)+SUMIF($N$8:$N$35,U9,$P$8:$P$35) -> 0 | X9: =IF($F$4=0,0,W9/$F$4) -> 0 | Z9: =U11 -> Beleza | AA9: =W11 -> 0
B10: Nome | D10: Pago? | E10: Data | F10: Tipo | G10: Categoria | H10: Valor | R10: Total | S10: =SUM(S8:S9) -> 0 | U10: Presentes | W10: =SUMIF($G$11:$G$18,U10,$H$11:$H$18)+SUMIF($G$24:$G$35,U10,$H$24:$H$35)+SUMIF($N$8:$N$35,U10,$P$8:$P$35) -> 0 | X10: =IF($F$4=0,0,W10/$F$4) -> 0 | Z10: =U12 -> Desenvolvimento | AA10: =W12 -> 0
U11: Beleza | W11: =SUMIF($G$11:$G$18,U11,$H$11:$H$18)+SUMIF($G$24:$G$35,U11,$H$24:$H$35)+SUMIF($N$8:$N$35,U11,$P$8:$P$35) -> 0 | X11: =IF($F$4=0,0,W11/$F$4) -> 0 | Z11: =U13 -> Lazer | AA11: =W13 -> 0
R12: Saídas | U12: Desenvolvimento | W12: =SUMIF($G$11:$G$18,U12,$H$11:$H$18)+SUMIF($G$24:$G$35,U12,$H$24:$H$35)+SUMIF($N$8:$N$35,U12,$P$8:$P$35) -> 0 | X12: =IF($F$4=0,0,W12/$F$4) -> 0 | Z12: =U14 -> Eletrônicos | AA12: =W14 -> 0
R13: Débito | S13: =SUMIF($F$11:$F$18,R13,$H$11:$H$18)+SUMIF($F$24:$F$35,R13,$H$24:$H$35)+SUMIF($M$8:$M$35,R13,$P$8:$P$35) -> 0 | U13: Lazer | W13: =SUMIF($G$11:$G$18,U13,$H$11:$H$18)+SUMIF($G$24:$G$35,U13,$H$24:$H$35)+SUMIF($N$8:$N$35,U13,$P$8:$P$35) -> 0 | X13: =IF($F$4=0,0,W13/$F$4) -> 0 | Z13: =U15 -> Assinaturas | AA13: =W15 -> 0
R14: Nubank | S14: =SUMIF($F$11:$F$18,R14,$H$11:$H$18)+SUMIF($F$24:$F$35,R14,$H$24:$H$35)+SUMIF($M$8:$M$35,R14,$P$8:$P$35) -> 0 | U14: Eletrônicos | W14: =SUMIF($G$11:$G$18,U14,$H$11:$H$18)+SUMIF($G$24:$G$35,U14,$H$24:$H$35)+SUMIF($N$8:$N$35,U14,$P$8:$P$35) -> 0 | X14: =IF($F$4=0,0,W14/$F$4) -> 0 | Z14: =U16 -> Uber transporte | AA14: =W16 -> 0
R15: Inter | S15: =SUMIF($F$11:$F$18,R15,$H$11:$H$18)+SUMIF($F$24:$F$35,R15,$H$24:$H$35)+SUMIF($M$8:$M$35,R15,$P$8:$P$35) -> 0 | U15: Assinaturas | W15: =SUMIF($G$11:$G$18,U15,$H$11:$H$18)+SUMIF($G$24:$G$35,U15,$H$24:$H$35)+SUMIF($N$8:$N$35,U15,$P$8:$P$35) -> 0 | X15: =IF($F$4=0,0,W15/$F$4) -> 0 | Z15: =U17 -> iFood/restaurante | AA15: =W17 -> 0
R16: Itaú | S16: =SUMIF($F$11:$F$18,R16,$H$11:$H$18)+SUMIF($F$24:$F$35,R16,$H$24:$H$35)+SUMIF($M$8:$M$35,R16,$P$8:$P$35) -> 0 | U16: Uber transporte | W16: =SUMIF($G$11:$G$18,U16,$H$11:$H$18)+SUMIF($G$24:$G$35,U16,$H$24:$H$35)+SUMIF($N$8:$N$35,U16,$P$8:$P$35) -> 0 | X16: =IF($F$4=0,0,W16/$F$4) -> 0 | Z16: =U18 -> Comida faculdade | AA16: =W18 -> 0
R17: Investimentos | S17: =S23 -> 0 | U17: iFood/restaurante | W17: =SUMIF($G$11:$G$18,U17,$H$11:$H$18)+SUMIF($G$24:$G$35,U17,$H$24:$H$35)+SUMIF($N$8:$N$35,U17,$P$8:$P$35) -> 0 | X17: =IF($F$4=0,0,W17/$F$4) -> 0 | Z17: =U19 -> Contas | AA17: =W19 -> 0
R18: Total | S18: =SUM(S13:S17) -> 0 | U18: Comida faculdade | W18: =SUMIF($G$11:$G$18,U18,$H$11:$H$18)+SUMIF($G$24:$G$35,U18,$H$24:$H$35)+SUMIF($N$8:$N$35,U18,$P$8:$P$35) -> 0 | X18: =IF($F$4=0,0,W18/$F$4) -> 0 | Z18: =U20 -> Outros | AA18: =W20 -> 0
U19: Contas | W19: =SUMIF($G$11:$G$18,U19,$H$11:$H$18)+SUMIF($G$24:$G$35,U19,$H$24:$H$35)+SUMIF($N$8:$N$35,U19,$P$8:$P$35) -> 0 | X19: =IF($F$4=0,0,W19/$F$4) -> 0
B20: Total de Parcelamentos | F20: =SUM(H24:H35) -> 0 | R20: Investimentos | U20: Outros | W20: =SUMIF($G$11:$G$18,U20,$H$11:$H$18)+SUMIF($G$24:$G$35,U20,$H$24:$H$35)+SUMIF($N$8:$N$35,U20,$P$8:$P$35) -> 0 | X20: =IF($F$4=0,0,W20/$F$4) -> 0
R21: Reserva
B22: Parcelamentos | R22: Renda fixa | U22: Gastos por tipo de pagamento
B23: Nome | D23: Parcelas | E23: Data | F23: Tipo | G23: Categoria | H23: Valor | R23: Total | S23: =SUM(S21:S22) -> 0 | U23: Tipo | V23: Valor | W23: Data | X23: Pago?
U24: Débito | V24: =S13 -> 0 | X24: ☐
U25: Nubank | V25: =S14 -> 0 | X25: ☐
U26: Inter | V26: =S15 -> 0 | X26: ☐
U27: Itaú | V27: =S16 -> 0 | X27: ☐
R30: Porcentagem de gastos por categoria

Sheet Dezembro
B2: Dezembro | Z2: Categoria | AA2: Valor gasto
R3: Saldo: | S3: =S10-S18 -> 0 | U3: Gastos do mês por categoria: | Z3: =U5 -> Mercado | AA3: =W5 -> 0
B4: Total de gastos: | F4: =F7+F20+N4 -> 0 | J4: Total de Gastos do Mês: | N4: =SUM(P8:P35) -> 0 | U4: Categoria | V4: Valor esperado | W4: Valor gasto | X4: Porcentagem | Z4: =U6 -> Despesas eventuais | AA4: =W6 -> 0
U5: Mercado | W5: =SUMIF($G$11:$G$18,U5,$H$11:$H$18)+SUMIF($G$24:$G$35,U5,$H$24:$H$35)+SUMIF($N$8:$N$35,U5,$P$8:$P$35) -> 0 | X5: =IF($F$4=0,0,W5/$F$4) -> 0 | Z5: =U7 -> Necessidades | AA5: =W7 -> 0
J6: Gastos do Mês | U6: Despesas eventuais | W6: =SUMIF($G$11:$G$18,U6,$H$11:$H$18)+SUMIF($G$24:$G$35,U6,$H$24:$H$35)+SUMIF($N$8:$N$35,U6,$P$8:$P$35) -> 0 | X6: =IF($F$4=0,0,W6/$F$4) -> 0 | Z6: =U8 -> Roupa | AA6: =W8 -> 0
B7: Total de Fixos: | F7: =SUM(H11:H18) -> 0 | J7: Nome | L7: Data | M7: Tipo | N7: Categoria | P7: Valor | R7: Entradas | U7: Necessidades | W7: =SUMIF($G$11:$G$18,U7,$H$11:$H$18)+SUMIF($G$24:$G$35,U7,$H$24:$H$35)+SUMIF($N$8:$N$35,U7,$P$8:$P$35) -> 0 | X7: =IF($F$4=0,0,W7/$F$4) -> 0 | Z7: =U9 -> Saúde | AA7: =W9 -> 0
R8: Salário | U8: Roupa | W8: =SUMIF($G$11:$G$18,U8,$H$11:$H$18)+SUMIF($G$24:$G$35,U8,$H$24:$H$35)+SUMIF($N$8:$N$35,U8,$P$8:$P$35) -> 0 | X8: =IF($F$4=0,0,W8/$F$4) -> 0 | Z8: =U10 -> Presentes | AA8: =W10 -> 0
B9: Fixos | R9: Bônus | U9: Saúde | W9: =SUMIF($G$11:$G$18,U9,$H$11:$H$18)+SUMIF($G$24:$G$35,U9,$H$24:$H$35)+SUMIF($N$8:$N$35,U9,$P$8:$P$35) -> 0 | X9: =IF($F$4=0,0,W9/$F$4) -> 0 | Z9: =U11 -> Beleza | AA9: =W11 -> 0
B10: Nome | D10: Pago? | E10: Data | F10: Tipo | G10: Categoria | H10: Valor | R10: Total | S10: =SUM(S8:S9) -> 0 | U10: Presentes | W10: =SUMIF($G$11:$G$18,U10,$H$11:$H$18)+SUMIF($G$24:$G$35,U10,$H$24:$H$35)+SUMIF($N$8:$N$35,U10,$P$8:$P$35) -> 0 | X10: =IF($F$4=0,0,W10/$F$4) -> 0 | Z10: =U12 -> Desenvolvimento | AA10: =W12 -> 0
U11: Beleza | W11: =SUMIF($G$11:$G$18,U11,$H$11:$H$18)+SUMIF($G$24:$G$35,U11,$H$24:$H$35)+SUMIF($N$8:$N$35,U11,$P$8:$P$35) -> 0 | X11: =IF($F$4=0,0,W11/$F$4) -> 0 | Z11: =U13 -> Lazer | AA11: =W13 -> 0
R12: Saídas | U12: Desenvolvimento | W12: =SUMIF($G$11:$G$18,U12,$H$11:$H$18)+SUMIF($G$24:$G$35,U12,$H$24:$H$35)+SUMIF($N$8:$N$35,U12,$P$8:$P$35) -> 0 | X12: =IF($F$4=0,0,W12/$F$4) -> 0 | Z12: =U14 -> Eletrônicos | AA12: =W14 -> 0
R13: Débito | S13: =SUMIF($F$11:$F$18,R13,$H$11:$H$18)+SUMIF($F$24:$F$35,R13,$H$24:$H$35)+SUMIF($M$8:$M$35,R13,$P$8:$P$35) -> 0 | U13: Lazer | W13: =SUMIF($G$11:$G$18,U13,$H$11:$H$18)+SUMIF($G$24:$G$35,U13,$H$24:$H$35)+SUMIF($N$8:$N$35,U13,$P$8:$P$35) -> 0 | X13: =IF($F$4=0,0,W13/$F$4) -> 0 | Z13: =U15 -> Assinaturas | AA13: =W15 -> 0
R14: Nubank | S14: =SUMIF($F$11:$F$18,R14,$H$11:$H$18)+SUMIF($F$24:$F$35,R14,$H$24:$H$35)+SUMIF($M$8:$M$35,R14,$P$8:$P$35) -> 0 | U14: Eletrônicos | W14: =SUMIF($G$11:$G$18,U14,$H$11:$H$18)+SUMIF($G$24:$G$35,U14,$H$24:$H$35)+SUMIF($N$8:$N$35,U14,$P$8:$P$35) -> 0 | X14: =IF($F$4=0,0,W14/$F$4) -> 0 | Z14: =U16 -> Uber transporte | AA14: =W16 -> 0
R15: Inter | S15: =SUMIF($F$11:$F$18,R15,$H$11:$H$18)+SUMIF($F$24:$F$35,R15,$H$24:$H$35)+SUMIF($M$8:$M$35,R15,$P$8:$P$35) -> 0 | U15: Assinaturas | W15: =SUMIF($G$11:$G$18,U15,$H$11:$H$18)+SUMIF($G$24:$G$35,U15,$H$24:$H$35)+SUMIF($N$8:$N$35,U15,$P$8:$P$35) -> 0 | X15: =IF($F$4=0,0,W15/$F$4) -> 0 | Z15: =U17 -> iFood/restaurante | AA15: =W17 -> 0
R16: Itaú | S16: =SUMIF($F$11:$F$18,R16,$H$11:$H$18)+SUMIF($F$24:$F$35,R16,$H$24:$H$35)+SUMIF($M$8:$M$35,R16,$P$8:$P$35) -> 0 | U16: Uber transporte | W16: =SUMIF($G$11:$G$18,U16,$H$11:$H$18)+SUMIF($G$24:$G$35,U16,$H$24:$H$35)+SUMIF($N$8:$N$35,U16,$P$8:$P$35) -> 0 | X16: =IF($F$4=0,0,W16/$F$4) -> 0 | Z16: =U18 -> Comida faculdade | AA16: =W18 -> 0
R17: Investimentos | S17: =S23 -> 0 | U17: iFood/restaurante | W17: =SUMIF($G$11:$G$18,U17,$H$11:$H$18)+SUMIF($G$24:$G$35,U17,$H$24:$H$35)+SUMIF($N$8:$N$35,U17,$P$8:$P$35) -> 0 | X17: =IF($F$4=0,0,W17/$F$4) -> 0 | Z17: =U19 -> Contas | AA17: =W19 -> 0
R18: Total | S18: =SUM(S13:S17) -> 0 | U18: Comida faculdade | W18: =SUMIF($G$11:$G$18,U18,$H$11:$H$18)+SUMIF($G$24:$G$35,U18,$H$24:$H$35)+SUMIF($N$8:$N$35,U18,$P$8:$P$35) -> 0 | X18: =IF($F$4=0,0,W18/$F$4) -> 0 | Z18: =U20 -> Outros | AA18: =W20 -> 0
U19: Contas | W19: =SUMIF($G$11:$G$18,U19,$H$11:$H$18)+SUMIF($G$24:$G$35,U19,$H$24:$H$35)+SUMIF($N$8:$N$35,U19,$P$8:$P$35) -> 0 | X19: =IF($F$4=0,0,W19/$F$4) -> 0
B20: Total de Parcelamentos | F20: =SUM(H24:H35) -> 0 | R20: Investimentos | U20: Outros | W20: =SUMIF($G$11:$G$18,U20,$H$11:$H$18)+SUMIF($G$24:$G$35,U20,$H$24:$H$35)+SUMIF($N$8:$N$35,U20,$P$8:$P$35) -> 0 | X20: =IF($F$4=0,0,W20/$F$4) -> 0
R21: Reserva
B22: Parcelamentos | R22: Renda fixa | U22: Gastos por tipo de pagamento
B23: Nome | D23: Parcelas | E23: Data | F23: Tipo | G23: Categoria | H23: Valor | R23: Total | S23: =SUM(S21:S22) -> 0 | U23: Tipo | V23: Valor | W23: Data | X23: Pago?
U24: Débito | V24: =S13 -> 0 | X24: ☐
U25: Nubank | V25: =S14 -> 0 | X25: ☐
U26: Inter | V26: =S15 -> 0 | X26: ☐
U27: Itaú | V27: =S16 -> 0 | X27: ☐
R30: Porcentagem de gastos por categoria

Sheet Resumo Anual
A1: Resumo Anual
A4: Categoria | B4: Jan | C4: Fev | D4: Mar | E4: Abr | F4: Mai | G4: Jun | H4: Jul | I4: Ago | J4: Set | K4: Out | L4: Nov | M4: Dez | N4: Total
A5: =Categorias!$A$5 -> Mercado | B5: =Janeiro!$W$5 -> 0 | C5: =Fevereiro!$W$5 -> 0 | D5: =Março!$W$5 -> 0 | E5: =Abril!$W$5 -> 0 | F5: =Maio!$W$5 -> 0 | G5: =Junho!$W$5 -> 0 | H5: =Julho!$W$5 -> 0 | I5: =Agosto!$W$5 -> 282 | J5: =Setembro!$W$5 -> 0 | K5: =Outubro!$W$5 -> 0 | L5: =Novembro!$W$5 -> 0 | M5: =Dezembro!$W$5 -> 0 | N5: =SUM(B5:M5) -> 282
A6: =Categorias!$A$6 -> Despesas eventuais | B6: =Janeiro!$W$6 -> 0 | C6: =Fevereiro!$W$6 -> 0 | D6: =Março!$W$6 -> 0 | E6: =Abril!$W$6 -> 0 | F6: =Maio!$W$6 -> 0 | G6: =Junho!$W$6 -> 0 | H6: =Julho!$W$6 -> 0 | I6: =Agosto!$W$6 -> 0 | J6: =Setembro!$W$6 -> 0 | K6: =Outubro!$W$6 -> 0 | L6: =Novembro!$W$6 -> 0 | M6: =Dezembro!$W$6 -> 0 | N6: =SUM(B6:M6) -> 0
A7: =Categorias!$A$7 -> Necessidades | B7: =Janeiro!$W$7 -> 0 | C7: =Fevereiro!$W$7 -> 0 | D7: =Março!$W$7 -> 0 | E7: =Abril!$W$7 -> 0 | F7: =Maio!$W$7 -> 0 | G7: =Junho!$W$7 -> 0 | H7: =Julho!$W$7 -> 0 | I7: =Agosto!$W$7 -> 58 | J7: =Setembro!$W$7 -> 130 | K7: =Outubro!$W$7 -> 0 | L7: =Novembro!$W$7 -> 0 | M7: =Dezembro!$W$7 -> 0 | N7: =SUM(B7:M7) -> 188
A8: =Categorias!$A$8 -> Roupa | B8: =Janeiro!$W$8 -> 0 | C8: =Fevereiro!$W$8 -> 0 | D8: =Março!$W$8 -> 0 | E8: =Abril!$W$8 -> 0 | F8: =Maio!$W$8 -> 0 | G8: =Junho!$W$8 -> 0 | H8: =Julho!$W$8 -> 0 | I8: =Agosto!$W$8 -> 248.5 | J8: =Setembro!$W$8 -> 0 | K8: =Outubro!$W$8 -> 0 | L8: =Novembro!$W$8 -> 0 | M8: =Dezembro!$W$8 -> 0 | N8: =SUM(B8:M8) -> 248.5
A9: =Categorias!$A$9 -> Saúde | B9: =Janeiro!$W$9 -> 0 | C9: =Fevereiro!$W$9 -> 0 | D9: =Março!$W$9 -> 0 | E9: =Abril!$W$9 -> 0 | F9: =Maio!$W$9 -> 0 | G9: =Junho!$W$9 -> 0 | H9: =Julho!$W$9 -> 0 | I9: =Agosto!$W$9 -> 158 | J9: =Setembro!$W$9 -> 0 | K9: =Outubro!$W$9 -> 0 | L9: =Novembro!$W$9 -> 0 | M9: =Dezembro!$W$9 -> 0 | N9: =SUM(B9:M9) -> 158
A10: =Categorias!$A$10 -> Presentes | B10: =Janeiro!$W$10 -> 0 | C10: =Fevereiro!$W$10 -> 0 | D10: =Março!$W$10 -> 0 | E10: =Abril!$W$10 -> 0 | F10: =Maio!$W$10 -> 0 | G10: =Junho!$W$10 -> 0 | H10: =Julho!$W$10 -> 0 | I10: =Agosto!$W$10 -> 0 | J10: =Setembro!$W$10 -> 0 | K10: =Outubro!$W$10 -> 0 | L10: =Novembro!$W$10 -> 0 | M10: =Dezembro!$W$10 -> 0 | N10: =SUM(B10:M10) -> 0
A11: =Categorias!$A$11 -> Beleza | B11: =Janeiro!$W$11 -> 0 | C11: =Fevereiro!$W$11 -> 0 | D11: =Março!$W$11 -> 0 | E11: =Abril!$W$11 -> 0 | F11: =Maio!$W$11 -> 0 | G11: =Junho!$W$11 -> 0 | H11: =Julho!$W$11 -> 0 | I11: =Agosto!$W$11 -> 332 | J11: =Setembro!$W$11 -> 0 | K11: =Outubro!$W$11 -> 0 | L11: =Novembro!$W$11 -> 0 | M11: =Dezembro!$W$11 -> 0 | N11: =SUM(B11:M11) -> 332
A12: =Categorias!$A$12 -> Desenvolvimento | B12: =Janeiro!$W$12 -> 0 | C12: =Fevereiro!$W$12 -> 0 | D12: =Março!$W$12 -> 0 | E12: =Abril!$W$12 -> 0 | F12: =Maio!$W$12 -> 0 | G12: =Junho!$W$12 -> 0 | H12: =Julho!$W$12 -> 0 | I12: =Agosto!$W$12 -> 0 | J12: =Setembro!$W$12 -> 170 | K12: =Outubro!$W$12 -> 0 | L12: =Novembro!$W$12 -> 0 | M12: =Dezembro!$W$12 -> 0 | N12: =SUM(B12:M12) -> 170
A13: =Categorias!$A$13 -> Lazer | B13: =Janeiro!$W$13 -> 0 | C13: =Fevereiro!$W$13 -> 0 | D13: =Março!$W$13 -> 0 | E13: =Abril!$W$13 -> 0 | F13: =Maio!$W$13 -> 0 | G13: =Junho!$W$13 -> 0 | H13: =Julho!$W$13 -> 0 | I13: =Agosto!$W$13 -> 0 | J13: =Setembro!$W$13 -> 0 | K13: =Outubro!$W$13 -> 0 | L13: =Novembro!$W$13 -> 0 | M13: =Dezembro!$W$13 -> 0 | N13: =SUM(B13:M13) -> 0
A14: =Categorias!$A$14 -> Eletrônicos | B14: =Janeiro!$W$14 -> 0 | C14: =Fevereiro!$W$14 -> 0 | D14: =Março!$W$14 -> 0 | E14: =Abril!$W$14 -> 0 | F14: =Maio!$W$14 -> 0 | G14: =Junho!$W$14 -> 0 | H14: =Julho!$W$14 -> 0 | I14: =Agosto!$W$14 -> 45 | J14: =Setembro!$W$14 -> 0 | K14: =Outubro!$W$14 -> 0 | L14: =Novembro!$W$14 -> 0 | M14: =Dezembro!$W$14 -> 0 | N14: =SUM(B14:M14) -> 45
A15: =Categorias!$A$15 -> Assinaturas | B15: =Janeiro!$W$15 -> 0 | C15: =Fevereiro!$W$15 -> 0 | D15: =Março!$W$15 -> 0 | E15: =Abril!$W$15 -> 0 | F15: =Maio!$W$15 -> 0 | G15: =Junho!$W$15 -> 0 | H15: =Julho!$W$15 -> 0 | I15: =Agosto!$W$15 -> 103.9 | J15: =Setembro!$W$15 -> 0 | K15: =Outubro!$W$15 -> 0 | L15: =Novembro!$W$15 -> 0 | M15: =Dezembro!$W$15 -> 0 | N15: =SUM(B15:M15) -> 103.9
A16: =Categorias!$A$16 -> Uber transporte | B16: =Janeiro!$W$16 -> 0 | C16: =Fevereiro!$W$16 -> 0 | D16: =Março!$W$16 -> 0 | E16: =Abril!$W$16 -> 0 | F16: =Maio!$W$16 -> 0 | G16: =Junho!$W$16 -> 0 | H16: =Julho!$W$16 -> 0 | I16: =Agosto!$W$16 -> 83 | J16: =Setembro!$W$16 -> 0 | K16: =Outubro!$W$16 -> 0 | L16: =Novembro!$W$16 -> 0 | M16: =Dezembro!$W$16 -> 0 | N16: =SUM(B16:M16) -> 83
A17: =Categorias!$A$17 -> iFood/restaurante | B17: =Janeiro!$W$17 -> 0 | C17: =Fevereiro!$W$17 -> 0 | D17: =Março!$W$17 -> 0 | E17: =Abril!$W$17 -> 0 | F17: =Maio!$W$17 -> 0 | G17: =Junho!$W$17 -> 0 | H17: =Julho!$W$17 -> 0 | I17: =Agosto!$W$17 -> 222.5 | J17: =Setembro!$W$17 -> 0 | K17: =Outubro!$W$17 -> 0 | L17: =Novembro!$W$17 -> 0 | M17: =Dezembro!$W$17 -> 0 | N17: =SUM(B17:M17) -> 222.5
A18: =Categorias!$A$18 -> Comida faculdade | B18: =Janeiro!$W$18 -> 0 | C18: =Fevereiro!$W$18 -> 0 | D18: =Março!$W$18 -> 0 | E18: =Abril!$W$18 -> 0 | F18: =Maio!$W$18 -> 0 | G18: =Junho!$W$18 -> 0 | H18: =Julho!$W$18 -> 0 | I18: =Agosto!$W$18 -> 48 | J18: =Setembro!$W$18 -> 0 | K18: =Outubro!$W$18 -> 0 | L18: =Novembro!$W$18 -> 0 | M18: =Dezembro!$W$18 -> 0 | N18: =SUM(B18:M18) -> 48
A19: =Categorias!$A$19 -> Contas | B19: =Janeiro!$W$19 -> 0 | C19: =Fevereiro!$W$19 -> 0 | D19: =Março!$W$19 -> 0 | E19: =Abril!$W$19 -> 0 | F19: =Maio!$W$19 -> 0 | G19: =Junho!$W$19 -> 0 | H19: =Julho!$W$19 -> 0 | I19: =Agosto!$W$19 -> 385 | J19: =Setembro!$W$19 -> 0 | K19: =Outubro!$W$19 -> 0 | L19: =Novembro!$W$19 -> 0 | M19: =Dezembro!$W$19 -> 0 | N19: =SUM(B19:M19) -> 385
A20: =Categorias!$A$20 -> Outros | B20: =Janeiro!$W$20 -> 0 | C20: =Fevereiro!$W$20 -> 0 | D20: =Março!$W$20 -> 0 | E20: =Abril!$W$20 -> 0 | F20: =Maio!$W$20 -> 0 | G20: =Junho!$W$20 -> 0 | H20: =Julho!$W$20 -> 0 | I20: =Agosto!$W$20 -> 0 | J20: =Setembro!$W$20 -> 0 | K20: =Outubro!$W$20 -> 0 | L20: =Novembro!$W$20 -> 0 | M20: =Dezembro!$W$20 -> 0 | N20: =SUM(B20:M20) -> 0
A22: Total de Gastos | B22: =Janeiro!$F$4 -> 0 | C22: =Fevereiro!$F$4 -> 0 | D22: =Março!$F$4 -> 0 | E22: =Abril!$F$4 -> 0 | F22: =Maio!$F$4 -> 0 | G22: =Junho!$F$4 -> 0 | H22: =Julho!$F$4 -> 0 | I22: =Agosto!$F$4 -> 1965.9 | J22: =Setembro!$F$4 -> 300 | K22: =Outubro!$F$4 -> 0 | L22: =Novembro!$F$4 -> 0 | M22: =Dezembro!$F$4 -> 0 | N22: =SUM(B22:M22) -> 2265.9
A23: Total de Entradas | B23: =Janeiro!$S$10 -> 0 | C23: =Fevereiro!$S$10 -> 0 | D23: =Março!$S$10 -> 0 | E23: =Abril!$S$10 -> 0 | F23: =Maio!$S$10 -> 0 | G23: =Junho!$S$10 -> 0 | H23: =Julho!$S$10 -> 0 | I23: =Agosto!$S$10 -> 2400 | J23: =Setembro!$S$10 -> 2500 | K23: =Outubro!$S$10 -> 0 | L23: =Novembro!$S$10 -> 0 | M23: =Dezembro!$S$10 -> 0 | N23: =SUM(B23:M23) -> 4900
A24: Saldo | B24: =Janeiro!$S$3 -> 0 | C24: =Fevereiro!$S$3 -> 0 | D24: =Março!$S$3 -> 0 | E24: =Abril!$S$3 -> 0 | F24: =Maio!$S$3 -> 0 | G24: =Junho!$S$3 -> 0 | H24: =Julho!$S$3 -> 0 | I24: =Agosto!$S$3 -> 184.1 | J24: =Setembro!$S$3 -> 1400 | K24: =Outubro!$S$3 -> 0 | L24: =Novembro!$S$3 -> 0 | M24: =Dezembro!$S$3 -> 0 | N24: =SUM(B24:M24) -> 1584.1

Sheet Categorias
A1: Categorias e formas de pagamento
A4: Categorias | B4: Cor | D4: Tipo de pagamento | E4: Cor
A5: Mercado | D5: Débito
A6: Despesas eventuais | D6: Nubank
A7: Necessidades | D7: Inter
A8: Roupa | D8: Itaú
A9: Saúde
A10: Presentes
A11: Beleza
A12: Desenvolvimento
A13: Lazer
A14: Eletrônicos
A15: Assinaturas
A16: Uber transporte
A17: iFood/restaurante
A18: Comida faculdade
A19: Contas
A20: Outros
A23: Referência visual: https://br.pinterest.com/pin/957296464540945222/
